{
  "metadata": {
    "url": "https://www.bundestag.de/apps/plenar/plenar/conferenceweekDetail.form?year=2015&week=21",
    "description": "2015_21"
  },
  "data": {
    "id": "2015_21",
    "previous": {
      "year": 2015,
      "week": 19
    },
    "this": {
      "year": 2015,
      "week": 21
    },
    "next": {
      "year": 2015,
      "week": 24
    },
    "sessions": [
      {
        "date": "2015-05-20T00:00:00.000Z",
        "dateText": "20. Mai 2015",
        "session": "105",
        "tops": [
          {
            "time": "2015-05-20T13:00:00.000Z",
            "top": "",
            "heading": null,
            "topic": [
              {
                "lines": [
                  "Sitzungseröffnung"
                ],
                "documents": [],
                "isVote": null
              }
            ],
            "status": []
          },
          {
            "time": "2015-05-20T13:00:00.000Z",
            "top": "1",
            "heading": "Erneuerbare-Energien-Gesetz",
            "topic": [
              {
                "lines": [
                  "Erste Beratung des von der Bundesregierung eingebrachten Entwurfs eines Zweiten Gesetzes zur Änderung des Erneuerbare-Energien-Gesetzes",
                  "Drucksache <a target='_blank' href=\"http://dip21.bundestag.de/dip21/btd/18/048/1804891.pdf\" class=\"dipLink\" title=\"Die PDF-Datei Drucksache 18/4891 öffnet sich in einem neuen Fenster\"><i class=\"icon-doc\"></i>18/4891</a>"
                ],
                "documents": [
                  "http://dip21.bundestag.de/dip21/btd/18/048/1804891.pdf"
                ],
                "isVote": false
              }
            ],
            "status": []
          },
          {
            "time": "2015-05-20T13:05:00.000Z",
            "top": "2",
            "heading": "Befragung der Bundesregierung",
            "topic": [
              {
                "lines": [
                  "Befragung der Bundesregierung",
                  "Thema: Agrarpolitischer Bericht 2015 der Bundesregierung"
                ],
                "documents": [],
                "isVote": null
              }
            ],
            "status": []
          },
          {
            "time": "2015-05-20T14:00:00.000Z",
            "top": "3",
            "heading": "Fragestunde",
            "topic": [
              {
                "lines": [
                  "Fragestunde",
                  "Drucksache <a target='_blank' href=\"http://dip21.bundestag.de/dip21/btd/18/049/1804907.pdf\" class=\"dipLink\" title=\"Die PDF-Datei Drucksache 18/4907 öffnet sich in einem neuen Fenster\"><i class=\"icon-doc\"></i>18/4907</a>, <a target='_blank' href=\"http://dip21.bundestag.de/dip21/btd/18/049/1804927.pdf\" class=\"dipLink\" title=\"Die PDF-Datei Drucksache 18/4927 öffnet sich in einem neuen Fenster\"><i class=\"icon-doc\"></i>18/4927</a>"
                ],
                "documents": [
                  "http://dip21.bundestag.de/dip21/btd/18/049/1804907.pdf",
                  "http://dip21.bundestag.de/dip21/btd/18/049/1804927.pdf"
                ],
                "isVote": null
              }
            ],
            "status": []
          },
          {
            "time": "2015-05-20T15:45:00.000Z",
            "top": "ZP 1",
            "heading": "Aktuelle Stunde zur Prognose des IWF",
            "topic": [
              {
                "lines": [
                  "Aktuelle Stunde",
                  "auf Verlangen der Fraktionen der CDU/CSU und SPD",
                  "Aktuelle Prognose des IWF – Perspektiven für Wirtschaft und Wettbewerbsfähigkeit Deutschlands"
                ],
                "documents": [],
                "isVote": null
              }
            ],
            "status": []
          },
          {
            "time": "2015-05-20T17:00:00.000Z",
            "top": "",
            "heading": null,
            "topic": [
              {
                "lines": [
                  "Sitzungsende"
                ],
                "documents": [],
                "isVote": null
              }
            ],
            "status": []
          }
        ]
      },
      {
        "date": "2015-05-21T00:00:00.000Z",
        "dateText": "21. Mai 2015",
        "session": "106",
        "tops": [
          {
            "time": "2015-05-21T09:00:00.000Z",
            "top": "",
            "heading": null,
            "topic": [
              {
                "lines": [
                  "Sitzungseröffnung"
                ],
                "documents": [],
                "isVote": null
              }
            ],
            "status": []
          },
          {
            "time": "2015-05-21T09:05:00.000Z",
            "top": "4",
            "heading": "Eidesleistung des Wehrbeauftragten",
            "topic": [
              {
                "lines": [
                  "Eidesleistung des Wehrbeauftragten"
                ],
                "documents": [],
                "isVote": null
              }
            ],
            "status": []
          },
          {
            "time": "2015-05-21T09:05:00.000Z",
            "top": "5",
            "heading": "Regierungserklärung zu Gipfeln Östliche Partnerschaft, G7- sowie EU-CELAC",
            "topic": [
              {
                "lines": [
                  "Abgabe einer Regierungserklärung durch die Bundeskanzlerin",
                  "zum Gipfel Östliche Partnerschaft am 21./22. Mai 2015 in Riga, zum G7-Gipfel am 7./8. Juni 2015 in Elmau und zum EU-Celac-Gipfel am 10./11. Juni 2015 in Brüssel"
                ],
                "documents": [],
                "isVote": null
              }
            ],
            "status": []
          },
          {
            "time": "2015-05-21T11:20:00.000Z",
            "top": "6",
            "heading": "Leiharbeit und Werkverträge",
            "topic": [
              {
                "lines": [
                  "Beratung des Antrags Fraktion DIE LINKE.",
                  "Leiharbeit und Werkverträge eingrenzen und umfassend regulieren",
                  "Drucksache <a target='_blank' href=\"http://dip21.bundestag.de/dip21/btd/18/048/1804839.pdf\" class=\"dipLink\" title=\"Die PDF-Datei Drucksache 18/4839 öffnet sich in einem neuen Fenster\"><i class=\"icon-doc\"></i>18/4839</a>"
                ],
                "documents": [
                  "http://dip21.bundestag.de/dip21/btd/18/048/1804839.pdf"
                ],
                "isVote": true
              }
            ],
            "status": []
          },
          {
            "time": "2015-05-21T13:05:00.000Z",
            "top": "7",
            "heading": "Berufliche und akademische Bildung",
            "topic": [
              {
                "lines": [
                  "a) Beratung des Antrags der Fraktionen der CDU/CSU und SPD",
                  "Prinzipien des deutschen Bildungswesens stärken - Gleichwertigkeit und Durchlässigkeit der beruflichen und der akademischen Bildung durchsetzen",
                  "Drucksache <a target='_blank' href=\"http://dip21.bundestag.de/dip21/btd/18/049/1804928.pdf\" class=\"dipLink\" title=\"Die PDF-Datei Drucksache 18/4928 öffnet sich in einem neuen Fenster\"><i class=\"icon-doc\"></i>18/4928</a>"
                ],
                "documents": [
                  "http://dip21.bundestag.de/dip21/btd/18/049/1804928.pdf"
                ],
                "isVote": true
              },
              {
                "lines": [
                  "b) Beratung der Unterrichtung durch die Bundesregierung",
                  "Berufsbildungsbericht 2015",
                  "Drucksache <a target='_blank' href=\"http://dip21.bundestag.de/dip21/btd/18/046/1804680.pdf\" class=\"dipLink\" title=\"Die PDF-Datei Drucksache 18/4680 öffnet sich in einem neuen Fenster\"><i class=\"icon-doc\"></i>18/4680</a>"
                ],
                "documents": [
                  "http://dip21.bundestag.de/dip21/btd/18/046/1804680.pdf"
                ],
                "isVote": null
              },
              {
                "lines": [
                  "c) Beratung des Antrags der Fraktion DIE LINKE.",
                  "Ausbildungsqualität sichern - Gute Ausbildung für alle schaffen",
                  "Drucksache <a target='_blank' href=\"http://dip21.bundestag.de/dip21/btd/18/049/1804931.pdf\" class=\"dipLink\" title=\"Die PDF-Datei Drucksache 18/4931 öffnet sich in einem neuen Fenster\"><i class=\"icon-doc\"></i>18/4931</a>"
                ],
                "documents": [
                  "http://dip21.bundestag.de/dip21/btd/18/049/1804931.pdf"
                ],
                "isVote": true
              },
              {
                "lines": [
                  "d) Beratung des Antrags der Fraktion BÜNDNIS 90/DIE GRÜNEN",
                  "Mit einer echten Ausbildungsgarantie das Recht auf Ausbildung umsetzen",
                  "Drucksache <a target='_blank' href=\"http://dip21.bundestag.de/dip21/btd/18/049/1804938.pdf\" class=\"dipLink\" title=\"Die PDF-Datei Drucksache 18/4938 öffnet sich in einem neuen Fenster\"><i class=\"icon-doc\"></i>18/4938</a>"
                ],
                "documents": [
                  "http://dip21.bundestag.de/dip21/btd/18/049/1804938.pdf"
                ],
                "isVote": true
              }
            ],
            "status": []
          },
          {
            "time": "2015-05-21T14:20:00.000Z",
            "top": "33 + ZP 2",
            "heading": "Überweisungen im vereinfachten Verfahren",
            "topic": [
              {
                "lines": [
                  "Überweisungen im vereinfachten Verfahren"
                ],
                "documents": [],
                "isVote": null
              }
            ],
            "status": []
          },
          {
            "time": "2015-05-21T14:20:00.000Z",
            "top": "34 + ZP 3",
            "heading": "Abschließende Beratungen ohne Aussprache",
            "topic": [
              {
                "lines": [
                  "Abschließende Beratungen ohne Aussprache"
                ],
                "documents": [],
                "isVote": null
              }
            ],
            "status": []
          },
          {
            "time": "2015-05-21T14:25:00.000Z",
            "top": "ZP 4",
            "heading": "Aktuelle Stunde zur Freigabe der NSA-Selektoren-Liste",
            "topic": [
              {
                "lines": [
                  "Aktuelle Stunde",
                  "auf Verlangen der Fraktion DIE LINKE.",
                  "Haltung der Koalitionsfraktionen zur Freigabe der NSA-Selektoren-Liste im Hinblick auf mögliche Ausspähungen von Wirtschaft und Politik"
                ],
                "documents": [],
                "isVote": null
              }
            ],
            "status": []
          },
          {
            "time": "2015-05-21T15:40:00.000Z",
            "top": "8",
            "heading": "Nachtragshaushalt und Unterstützung von Kommunen",
            "topic": [
              {
                "lines": [
                  "a) Zweite und dritte Beratung des von der Bundesregierung",
                  "eingebrachten Entwurfs eines Gesetzes über die Feststellung eines Nachtrags zum Bundeshaushaltsplan für das Haushaltsjahr 2015",
                  "(Nachtragshaushaltsgesetz 2015)",
                  "Drucksache <a target='_blank' href=\"http://dip21.bundestag.de/dip21/btd/18/046/1804600.pdf\" class=\"dipLink\" title=\"Die PDF-Datei Drucksache 18/4600 öffnet sich in einem neuen Fenster\"><i class=\"icon-doc\"></i>18/4600</a>",
                  "Beschlussempfehlung und Bericht des Haushaltsausschusses (8. Ausschuss)",
                  "Drucksache 18/…"
                ],
                "documents": [
                  "http://dip21.bundestag.de/dip21/btd/18/046/1804600.pdf"
                ],
                "isVote": true
              },
              {
                "lines": [
                  "b) Zweite und dritte Beratung des von der Bundesregierung",
                  "eingebrachten Entwurfs eines Gesetzes zur Förderung von Investitionen finanzschwacher Kommunen und zur Entlastung von Ländern und Kommunen bei der Aufnahme und Unterbringung von Asylbewerbern",
                  "Drucksache <a target='_blank' href=\"http://dip21.bundestag.de/dip21/btd/18/046/1804653.pdf\" class=\"dipLink\" title=\"Die PDF-Datei Drucksache 18/4653 öffnet sich in einem neuen Fenster\"><i class=\"icon-doc\"></i>18/4653</a> (neu)",
                  "Beschlussempfehlung und Bericht des Haushaltsausschusses (8. Ausschuss)",
                  "Drucksache <a target='_blank' href=\"http://dip21.bundestag.de/dip21/btd/18/049/1804975.pdf\" class=\"dipLink\" title=\"Die PDF-Datei Drucksache 18/4975 öffnet sich in einem neuen Fenster\"><i class=\"icon-doc\"></i>18/4975</a>"
                ],
                "documents": [
                  "http://dip21.bundestag.de/dip21/btd/18/046/1804653.pdf",
                  "http://dip21.bundestag.de/dip21/btd/18/049/1804975.pdf"
                ],
                "isVote": true
              },
              {
                "lines": [
                  "c) Beratung der Beschlussempfehlung und des Berichts des Haushaltsausschusses (8. Ausschuss)",
                  "zu dem Antrag der Fraktion DIE LINKE.",
                  "Bundesverantwortung wahrnehmen - Kommunen bei Unterbringung von Flüchtlingen und Asylbewerbern sofort helfen und Kosten der Unterkunft für Hartz-IV-Leistungsberechtigte schrittweise übernehmen",
                  "Drucksachen <a target='_blank' href=\"http://dip21.bundestag.de/dip21/btd/18/035/1803573.pdf\" class=\"dipLink\" title=\"Die PDF-Datei Drucksache 18/3573 öffnet sich in einem neuen Fenster\"><i class=\"icon-doc\"></i>18/3573</a>, <a target='_blank' href=\"http://dip21.bundestag.de/dip21/btd/18/041/1804118.pdf\" class=\"dipLink\" title=\"Die PDF-Datei Drucksache 18/4118 öffnet sich in einem neuen Fenster\"><i class=\"icon-doc\"></i>18/4118</a>"
                ],
                "documents": [
                  "http://dip21.bundestag.de/dip21/btd/18/035/1803573.pdf",
                  "http://dip21.bundestag.de/dip21/btd/18/041/1804118.pdf"
                ],
                "isVote": true
              },
              {
                "lines": [
                  "d) Beratung der Beschlussempfehlung und des Berichts des Haushaltsausschusses (8. Ausschuss)",
                  "zu dem Antrag der Fraktion BÜNDNIS 90/DIE GRÜNEN",
                  "Heute für morgen investieren - Damit unsere Zukunft nachhaltig und gerechter wird",
                  "Drucksachen <a target='_blank' href=\"http://dip21.bundestag.de/dip21/btd/18/046/1804689.pdf\" class=\"dipLink\" title=\"Die PDF-Datei Drucksache 18/4689 öffnet sich in einem neuen Fenster\"><i class=\"icon-doc\"></i>18/4689</a>, <a target='_blank' href=\"http://dip21.bundestag.de/dip21/btd/18/049/1804974.pdf\" class=\"dipLink\" title=\"Die PDF-Datei Drucksache 18/4974 öffnet sich in einem neuen Fenster\"><i class=\"icon-doc\"></i>18/4974</a>"
                ],
                "documents": [
                  "http://dip21.bundestag.de/dip21/btd/18/046/1804689.pdf",
                  "http://dip21.bundestag.de/dip21/btd/18/049/1804974.pdf"
                ],
                "isVote": true
              }
            ],
            "status": []
          },
          {
            "time": "2015-05-21T16:35:00.000Z",
            "top": "9",
            "heading": "Studienförderung und Studienfinanzierung",
            "topic": [
              {
                "lines": [
                  "Beratung des Antrags der Fraktion BÜNDNIS 90/DIE GRÜNEN",
                  "Deutschlandstipendium abschaffen - Stipendienförderung und Studienfinanzierung stärken",
                  "Drucksache <a target='_blank' href=\"http://dip21.bundestag.de/dip21/btd/18/046/1804692.pdf\" class=\"dipLink\" title=\"Die PDF-Datei Drucksache 18/4692 öffnet sich in einem neuen Fenster\"><i class=\"icon-doc\"></i>18/4692</a>"
                ],
                "documents": [
                  "http://dip21.bundestag.de/dip21/btd/18/046/1804692.pdf"
                ],
                "isVote": true
              }
            ],
            "status": []
          },
          {
            "time": "2015-05-21T17:25:00.000Z",
            "top": "10 + ZP 5",
            "heading": "Europäischer Fonds für strategische Investitionen",
            "topic": [
              {
                "lines": [
                  "Beratung des Antrags der Fraktionen der CDU/CSU und SPD",
                  "zu dem Vorschlag für eine Verordnung des Europäischen Parlaments und des Rates über den Europäischen Fonds für strategische Investitionen und zur Änderung der Verordnungen (EU) Nr. 1291/2013 und (EU) Nr. 1316/2013",
                  "KOM(2015) 10 endg.; Ratsdok. 5112/15",
                  "hier:\tStellungnahme gegenüber der Bundesregierung gemäß Artikel 23 Absatz 3 des Grundgesetzes",
                  "Dem Europäischen Fonds für strategische Investitionen zum Erfolg verhelfen",
                  "Drucksache <a target='_blank' href=\"http://dip21.bundestag.de/dip21/btd/18/049/1804929.pdf\" class=\"dipLink\" title=\"Die PDF-Datei Drucksache 18/4929 öffnet sich in einem neuen Fenster\"><i class=\"icon-doc\"></i>18/4929</a>"
                ],
                "documents": [
                  "http://dip21.bundestag.de/dip21/btd/18/049/1804929.pdf"
                ],
                "isVote": true
              },
              {
                "lines": [
                  "ZP 5) Beratung des Antrags der Fraktion DIE LINKE.",
                  "Für ein öffentliches sozial-ökologisches Zukunftsinvestitionsprogramm in Europa",
                  "Drucksache <a target='_blank' href=\"http://dip21.bundestag.de/dip21/btd/18/049/1804932.pdf\" class=\"dipLink\" title=\"Die PDF-Datei Drucksache 18/4932 öffnet sich in einem neuen Fenster\"><i class=\"icon-doc\"></i>18/4932</a>"
                ],
                "documents": [
                  "http://dip21.bundestag.de/dip21/btd/18/049/1804932.pdf"
                ],
                "isVote": true
              }
            ],
            "status": []
          },
          {
            "time": "2015-05-21T18:10:00.000Z",
            "top": "11",
            "heading": "Finanzierung der Beseitigung von Rüstungsaltlasten",
            "topic": [
              {
                "lines": [
                  "Erste Beratung des von der Fraktion DIE LINKE.",
                  "eingebrachten Entwurfs eines Gesetzes über die Finanzierung der Beseitigung von Rüstungsaltlasten in der Bundesrepublik Deutschland (Rüstungsaltlastenfinanzierungsgesetz – RüstAltFG)",
                  "Drucksache <a target='_blank' href=\"http://dip21.bundestag.de/dip21/btd/18/048/1804841.pdf\" class=\"dipLink\" title=\"Die PDF-Datei Drucksache 18/4841 öffnet sich in einem neuen Fenster\"><i class=\"icon-doc\"></i>18/4841</a>"
                ],
                "documents": [
                  "http://dip21.bundestag.de/dip21/btd/18/048/1804841.pdf"
                ],
                "isVote": false
              }
            ],
            "status": []
          },
          {
            "time": "2015-05-21T18:50:00.000Z",
            "top": "12",
            "heading": "Bundeswehreinsatz Operation Atalanta",
            "topic": [
              {
                "lines": [
                  "Beratung der Beschlussempfehlung und des Berichts des Auswärtigen Ausschusses (3. Ausschuss)",
                  "zu dem Antrag der Bundesregierung",
                  "Fortsetzung der Beteiligung bewaffneter deutscher Streitkräfte an der EU-geführten Operation Atalanta zur Bekämpfung der Piraterie vor der Küste Somalias auf Grundlage des Seerechtsübereinkommens der Vereinten Nationen (VN) von 1982 und der Resolutionen 1814 (2008) vom 15. Mai 2008, 1816 (2008) vom 2. Juni 2008, 1838 (2008) vom 7. Oktober 2008, 1846 (2008) vom 2. Dezember 2008, 1851 (2008) vom 16. Dezember 2008, 1897 (2009) vom 30. November 2009, 1950 (2010) vom 23. November 2010, 2020 (2011) vom 22. November 2011, 2077 (2012) vom 21. November 2012, 2125 (2013) vom 18. November 2013, 2184 (2014) vom 12. November 2014 und nachfolgender Resolutionen des Sicherheitsrates der VN in Verbindung mit der Gemeinsamen Aktion 2008/851/GASP des Rates der Europäischen Union (EU) vom 10. November 2008, dem Beschluss 2009/907/GASP des Rates der EU vom 8. Dezember 2009, dem Beschluss 2010/437/GASP des Rates der EU vom 30. Juli 2010, dem Beschluss 2010/766/GASP des Rates der EU vom 7. Dezember 2010, dem Beschluss 2012/174/GASP des Rates der EU vom 23. März 2012 und dem Beschluss 2014/827/GASP vom 21. November 2014",
                  "Drucksachen <a target='_blank' href=\"http://dip21.bundestag.de/dip21/btd/18/047/1804769.pdf\" class=\"dipLink\" title=\"Die PDF-Datei Drucksache 18/4769 öffnet sich in einem neuen Fenster\"><i class=\"icon-doc\"></i>18/4769</a>, <a target='_blank' href=\"http://dip21.bundestag.de/dip21/btd/18/049/1804964.pdf\" class=\"dipLink\" title=\"Die PDF-Datei Drucksache 18/4964 öffnet sich in einem neuen Fenster\"><i class=\"icon-doc\"></i>18/4964</a>",
                  "- Bericht des Haushaltsausschusses (8. Ausschuss) gemäß § 96 der Geschäftsordnung",
                  "Drucksache <a target='_blank' href=\"http://dip21.bundestag.de/dip21/btd/18/049/1804976.pdf\" class=\"dipLink\" title=\"Die PDF-Datei Drucksache 18/4976 öffnet sich in einem neuen Fenster\"><i class=\"icon-doc\"></i>18/4976</a>"
                ],
                "documents": [
                  "http://dip21.bundestag.de/dip21/btd/18/047/1804769.pdf",
                  "http://dip21.bundestag.de/dip21/btd/18/049/1804964.pdf",
                  "http://dip21.bundestag.de/dip21/btd/18/049/1804976.pdf"
                ],
                "isVote": true
              }
            ],
            "status": []
          },
          {
            "time": "2015-05-21T19:40:00.000Z",
            "top": "13",
            "heading": "Rückführung von Wertstoffen in den Abfallkreislauf",
            "topic": [
              {
                "lines": [
                  "Beratung des Antrags der Fraktion BÜNDNIS 90/DIE GRÜNEN",
                  "Wertstoffgesetz jetzt vorlegen",
                  "Drucksache <a target='_blank' href=\"http://dip21.bundestag.de/dip21/btd/18/046/1804648.pdf\" class=\"dipLink\" title=\"Die PDF-Datei Drucksache 18/4648 öffnet sich in einem neuen Fenster\"><i class=\"icon-doc\"></i>18/4648</a>"
                ],
                "documents": [
                  "http://dip21.bundestag.de/dip21/btd/18/046/1804648.pdf"
                ],
                "isVote": true
              }
            ],
            "status": []
          },
          {
            "time": "2015-05-21T20:10:00.000Z",
            "top": "14",
            "heading": "Bundeswehreinsatz UNMIL in Liberia",
            "topic": [
              {
                "lines": [
                  "Beratung der Beschlussempfehlung und des Berichts des Auswärtigen Ausschusses (3. Ausschuss)",
                  "zu dem Antrag der Bundesregierung",
                  "Beteiligung bewaffneter deutscher Streitkräfte an der durch die Vereinten Nationen geführten Mission UNMIL in Liberia auf Grundlage der Resolution 1509 (2003) und nachfolgender Verlängerungsresolutionen des Sicherheitsrates der Vereinten Nationen, zuletzt Resolution 2190 (2014) vom 15. Dezember 2014 und der Resolution 2215 (2015) vom 2. April 2015",
                  "Drucksachen <a target='_blank' href=\"http://dip21.bundestag.de/dip21/btd/18/047/1804768.pdf\" class=\"dipLink\" title=\"Die PDF-Datei Drucksache 18/4768 öffnet sich in einem neuen Fenster\"><i class=\"icon-doc\"></i>18/4768</a>, <a target='_blank' href=\"http://dip21.bundestag.de/dip21/btd/18/049/1804965.pdf\" class=\"dipLink\" title=\"Die PDF-Datei Drucksache 18/4965 öffnet sich in einem neuen Fenster\"><i class=\"icon-doc\"></i>18/4965</a>",
                  "- Bericht des Haushaltsausschusses (8. Ausschuss) gemäß § 96 der Geschäftsordnung",
                  "Drucksache <a target='_blank' href=\"http://dip21.bundestag.de/dip21/btd/18/049/1804977.pdf\" class=\"dipLink\" title=\"Die PDF-Datei Drucksache 18/4977 öffnet sich in einem neuen Fenster\"><i class=\"icon-doc\"></i>18/4977</a>"
                ],
                "documents": [
                  "http://dip21.bundestag.de/dip21/btd/18/047/1804768.pdf",
                  "http://dip21.bundestag.de/dip21/btd/18/049/1804965.pdf",
                  "http://dip21.bundestag.de/dip21/btd/18/049/1804977.pdf"
                ],
                "isVote": true
              }
            ],
            "status": []
          },
          {
            "time": "2015-05-21T20:45:00.000Z",
            "top": "15",
            "heading": "Menschenrechte in Mexiko",
            "topic": [
              {
                "lines": [
                  "a) Beratung der Beschlussempfehlung und des Berichts des Ausschusses für Menschenrechte und humanitäre Hilfe (17. Ausschuss)",
                  "- zu dem Antrag der Fraktion DIE LINKE.",
                  "Menschenrechte in Mexiko schützen, Verhandlungen zum Sicherheitsabkommen aussetzen",
                  "- zu dem Antrag der Fraktion BÜNDNIS 90/DIE GRÜNEN",
                  "Iguala ist kein Einzelfall - Zur Menschenrechtslage in Mexiko",
                  "Drucksachen <a target='_blank' href=\"http://dip21.bundestag.de/dip21/btd/18/035/1803548.pdf\" class=\"dipLink\" title=\"Die PDF-Datei Drucksache 18/3548 öffnet sich in einem neuen Fenster\"><i class=\"icon-doc\"></i>18/3548</a>, <a target='_blank' href=\"http://dip21.bundestag.de/dip21/btd/18/035/1803552.pdf\" class=\"dipLink\" title=\"Die PDF-Datei Drucksache 18/3552 öffnet sich in einem neuen Fenster\"><i class=\"icon-doc\"></i>18/3552</a>, <a target='_blank' href=\"http://dip21.bundestag.de/dip21/btd/18/039/1803952.pdf\" class=\"dipLink\" title=\"Die PDF-Datei Drucksache 18/3952 öffnet sich in einem neuen Fenster\"><i class=\"icon-doc\"></i>18/3952</a>"
                ],
                "documents": [
                  "http://dip21.bundestag.de/dip21/btd/18/035/1803548.pdf",
                  "http://dip21.bundestag.de/dip21/btd/18/035/1803552.pdf",
                  "http://dip21.bundestag.de/dip21/btd/18/039/1803952.pdf"
                ],
                "isVote": true
              },
              {
                "lines": [
                  "b) Beratung der Beschlussempfehlung und des Berichts des Innenausschusses (4. Ausschuss)",
                  "zu dem Antrag Fraktion BÜNDNIS 90/DIE GRÜNEN",
                  "Sicherheitsabkommen brauchen Standards",
                  "Drucksachen <a target='_blank' href=\"http://dip21.bundestag.de/dip21/btd/18/035/1803553.pdf\" class=\"dipLink\" title=\"Die PDF-Datei Drucksache 18/3553 öffnet sich in einem neuen Fenster\"><i class=\"icon-doc\"></i>18/3553</a>, <a target='_blank' href=\"http://dip21.bundestag.de/dip21/btd/18/039/1803933.pdf\" class=\"dipLink\" title=\"Die PDF-Datei Drucksache 18/3933 öffnet sich in einem neuen Fenster\"><i class=\"icon-doc\"></i>18/3933</a>"
                ],
                "documents": [
                  "http://dip21.bundestag.de/dip21/btd/18/035/1803553.pdf",
                  "http://dip21.bundestag.de/dip21/btd/18/039/1803933.pdf"
                ],
                "isVote": true
              }
            ],
            "status": []
          },
          {
            "time": "2015-05-21T21:20:00.000Z",
            "top": "16 + ZP 6",
            "heading": "Erneuerbare-Energien-Gesetz",
            "topic": [
              {
                "lines": [
                  "Zweite und dritte Beratung des von den Fraktionen der CDU/CSU und SPD eingebrachten Entwurfs eines Zweiten Gesetzes zur Änderung des Erneuerbare-Energien-Gesetzes",
                  "Drucksache <a target='_blank' href=\"http://dip21.bundestag.de/dip21/btd/18/046/1804683.pdf\" class=\"dipLink\" title=\"Die PDF-Datei Drucksache 18/4683 öffnet sich in einem neuen Fenster\"><i class=\"icon-doc\"></i>18/4683</a>",
                  "- Zweite und dritte Beratung des von der Bundesregierung eingebrachten Entwurfs eines Zweiten Gesetzes zur Änderung des Erneuerbare-Energien-Gesetzes",
                  "Drucksache <a target='_blank' href=\"http://dip21.bundestag.de/dip21/btd/18/048/1804891.pdf\" class=\"dipLink\" title=\"Die PDF-Datei Drucksache 18/4891 öffnet sich in einem neuen Fenster\"><i class=\"icon-doc\"></i>18/4891</a>",
                  "Beschlussempfehlung und Bericht des Ausschusses für Wirtschaft und Energie (9. Ausschuss)",
                  "Drucksache <a target='_blank' href=\"http://dip21.bundestag.de/dip21/btd/18/049/1804968.pdf\" class=\"dipLink\" title=\"Die PDF-Datei Drucksache 18/4968 öffnet sich in einem neuen Fenster\"><i class=\"icon-doc\"></i>18/4968</a>"
                ],
                "documents": [
                  "http://dip21.bundestag.de/dip21/btd/18/046/1804683.pdf",
                  "http://dip21.bundestag.de/dip21/btd/18/048/1804891.pdf",
                  "http://dip21.bundestag.de/dip21/btd/18/049/1804968.pdf"
                ],
                "isVote": true
              },
              {
                "lines": [
                  "ZP 6) Beratung der Beschlussempfehlung und des Berichts des Ausschusses für Wirtschaft und Energie (9. Ausschuss) zu dem Antrag der Fraktion BÜNDNIS 90/DIE GRÜNEN",
                  "Europarechtskonforme Regelung der Industrievergünstigungen auf stromintensive Unternehmen im internationalen Wettbewerb begrenzen und das EEG als kosteneffizientes Instrument fortführen",
                  "Drucksachen <a target='_blank' href=\"http://dip21.bundestag.de/dip21/btd/18/002/1800291.pdf\" class=\"dipLink\" title=\"Die PDF-Datei Drucksache 18/291 öffnet sich in einem neuen Fenster\"><i class=\"icon-doc\"></i>18/291</a>, <a target='_blank' href=\"http://dip21.bundestag.de/dip21/btd/18/005/1800515.pdf\" class=\"dipLink\" title=\"Die PDF-Datei Drucksache 18/515 öffnet sich in einem neuen Fenster\"><i class=\"icon-doc\"></i>18/515</a>"
                ],
                "documents": [
                  "http://dip21.bundestag.de/dip21/btd/18/002/1800291.pdf",
                  "http://dip21.bundestag.de/dip21/btd/18/005/1800515.pdf"
                ],
                "isVote": true
              }
            ],
            "status": []
          },
          {
            "time": "2015-05-21T21:50:00.000Z",
            "top": "17",
            "heading": "Völkermord an den Rohingya",
            "topic": [
              {
                "lines": [
                  "Beratung der Beschlussempfehlung und des Berichts des Ausschusses für Menschenrechte und humanitäre Hilfe (17. Ausschuss)",
                  "zu dem Antrag Fraktion BÜNDNIS 90/DIE GRÜNEN",
                  "Verfolgt, vertrieben, vergessen - Völkermord an den Rohingya verhindern",
                  "Drucksachen <a target='_blank' href=\"http://dip21.bundestag.de/dip21/btd/18/026/1802615.pdf\" class=\"dipLink\" title=\"Die PDF-Datei Drucksache 18/2615 öffnet sich in einem neuen Fenster\"><i class=\"icon-doc\"></i>18/2615</a>, <a target='_blank' href=\"http://dip21.bundestag.de/dip21/btd/18/039/1803951.pdf\" class=\"dipLink\" title=\"Die PDF-Datei Drucksache 18/3951 öffnet sich in einem neuen Fenster\"><i class=\"icon-doc\"></i>18/3951</a>"
                ],
                "documents": [
                  "http://dip21.bundestag.de/dip21/btd/18/026/1802615.pdf",
                  "http://dip21.bundestag.de/dip21/btd/18/039/1803951.pdf"
                ],
                "isVote": true
              }
            ],
            "status": []
          },
          {
            "time": "2015-05-21T22:20:00.000Z",
            "top": "18 *",
            "heading": "Änderung soldatenrechtlicher Vorschriften",
            "topic": [
              {
                "lines": [
                  "Zweite und dritte Beratung des von der Bundesregierung",
                  "eingebrachten Entwurfs eines Gesetzes zur Neuregelung der Unterhaltssicherung sowie zur Änderung soldatenrechtlicher Vorschriften",
                  "Drucksache <a target='_blank' href=\"http://dip21.bundestag.de/dip21/btd/18/046/1804632.pdf\" class=\"dipLink\" title=\"Die PDF-Datei Drucksache 18/4632 öffnet sich in einem neuen Fenster\"><i class=\"icon-doc\"></i>18/4632</a>",
                  "Beschlussempfehlung und Bericht des Verteidigungsausschusses (12. Ausschuss)",
                  "Drucksache <a target='_blank' href=\"http://dip21.bundestag.de/dip21/btd/18/048/1804851.pdf\" class=\"dipLink\" title=\"Die PDF-Datei Drucksache 18/4851 öffnet sich in einem neuen Fenster\"><i class=\"icon-doc\"></i>18/4851</a>",
                  "- Bericht des Haushaltsausschusses (8. Ausschuss) gemäß § 96 der Geschäftsordnung",
                  "Drucksache <a target='_blank' href=\"http://dip21.bundestag.de/dip21/btd/18/048/1804852.pdf\" class=\"dipLink\" title=\"Die PDF-Datei Drucksache 18/4852 öffnet sich in einem neuen Fenster\"><i class=\"icon-doc\"></i>18/4852</a>"
                ],
                "documents": [
                  "http://dip21.bundestag.de/dip21/btd/18/046/1804632.pdf",
                  "http://dip21.bundestag.de/dip21/btd/18/048/1804851.pdf",
                  "http://dip21.bundestag.de/dip21/btd/18/048/1804852.pdf"
                ],
                "isVote": true
              }
            ],
            "status": []
          },
          {
            "time": "2015-05-21T22:25:00.000Z",
            "top": "19 *",
            "heading": "Internationales Staateninsolvenzverfahren",
            "topic": [
              {
                "lines": [
                  "Beratung der Beschlussempfehlung und des Berichts des Finanzausschusses (7. Ausschuss)",
                  "- zu dem Antrag der Fraktion DIE LINKE.",
                  "Für ein internationales Staateninsolvenzverfahren",
                  "- zu dem Antrag der Fraktion BÜNDNIS 90/DIE GRÜNEN",
                  "Resolution der Vereinten Nationen für ein multilaterales Rahmenwerk zur Restrukturierung von Staatsschulden umsetzen - Jetzt aktiv den Arbeitsprozess der Vereinten Nationen mitgestalten",
                  "Drucksachen <a target='_blank' href=\"http://dip21.bundestag.de/dip21/btd/18/037/1803743.pdf\" class=\"dipLink\" title=\"Die PDF-Datei Drucksache 18/3743 öffnet sich in einem neuen Fenster\"><i class=\"icon-doc\"></i>18/3743</a>, <a target='_blank' href=\"http://dip21.bundestag.de/dip21/btd/18/039/1803916.pdf\" class=\"dipLink\" title=\"Die PDF-Datei Drucksache 18/3916 öffnet sich in einem neuen Fenster\"><i class=\"icon-doc\"></i>18/3916</a>, <a target='_blank' href=\"http://dip21.bundestag.de/dip21/btd/18/042/1804233.pdf\" class=\"dipLink\" title=\"Die PDF-Datei Drucksache 18/4233 öffnet sich in einem neuen Fenster\"><i class=\"icon-doc\"></i>18/4233</a>"
                ],
                "documents": [
                  "http://dip21.bundestag.de/dip21/btd/18/037/1803743.pdf",
                  "http://dip21.bundestag.de/dip21/btd/18/039/1803916.pdf",
                  "http://dip21.bundestag.de/dip21/btd/18/042/1804233.pdf"
                ],
                "isVote": true
              }
            ],
            "status": []
          },
          {
            "time": "2015-05-21T22:25:00.000Z",
            "top": "20 *",
            "heading": "Elektro- und Elektronikgerätegesetz",
            "topic": [
              {
                "lines": [
                  "Erste Beratung des von der Bundesregierung",
                  "eingebrachten Entwurfs eines Gesetzes zur Neuordnung des Rechts über das Inverkehrbringen, die Rücknahme und die umweltverträgliche Entsorgung von Elektro- und Elektronikgeräten (Elektro- und Elektronikgerätegesetz - ElektroG)",
                  "Drucksache <a target='_blank' href=\"http://dip21.bundestag.de/dip21/btd/18/049/1804901.pdf\" class=\"dipLink\" title=\"Die PDF-Datei Drucksache 18/4901 öffnet sich in einem neuen Fenster\"><i class=\"icon-doc\"></i>18/4901</a>"
                ],
                "documents": [
                  "http://dip21.bundestag.de/dip21/btd/18/049/1804901.pdf"
                ],
                "isVote": false
              }
            ],
            "status": []
          },
          {
            "time": "2015-05-21T22:25:00.000Z",
            "top": "22 *",
            "heading": "Vernachlässigte armutsassoziierte Erkrankungen",
            "topic": [
              {
                "lines": [
                  "Beratung des Antrags der Fraktionen der CDU/CSU und SPD",
                  "Forschung und Entwicklung für die Bekämpfung von vernachlässigten armutsassoziierten Erkrankungen stärken",
                  "Drucksache <a target='_blank' href=\"http://dip21.bundestag.de/dip21/btd/18/049/1804930.pdf\" class=\"dipLink\" title=\"Die PDF-Datei Drucksache 18/4930 öffnet sich in einem neuen Fenster\"><i class=\"icon-doc\"></i>18/4930</a>"
                ],
                "documents": [
                  "http://dip21.bundestag.de/dip21/btd/18/049/1804930.pdf"
                ],
                "isVote": true
              }
            ],
            "status": []
          },
          {
            "time": "2015-05-21T22:25:00.000Z",
            "top": "23",
            "heading": "Bundesverfassungsgerichtsgesetz",
            "topic": [
              {
                "lines": [
                  "Zweite und dritte Beratung des von den Fraktionen CDU/CSU, SPD, DIE LINKE. und BÜNDNIS 90/DIE GRÜNEN",
                  "eingebrachten Entwurfs eines Neunten Gesetzes zur Änderung des Bundesverfassungsgerichtsgesetzes (9. BVerfGGÄndG)",
                  "Drucksache <a target='_blank' href=\"http://dip21.bundestag.de/dip21/btd/18/027/1802737.pdf\" class=\"dipLink\" title=\"Die PDF-Datei Drucksache 18/2737 öffnet sich in einem neuen Fenster\"><i class=\"icon-doc\"></i>18/2737</a>",
                  "Beschlussempfehlung und Bericht des Ausschusses für Recht und Verbraucherschutz (6. Ausschuss)",
                  "Drucksache <a target='_blank' href=\"http://dip21.bundestag.de/dip21/btd/18/049/1804963.pdf\" class=\"dipLink\" title=\"Die PDF-Datei Drucksache 18/4963 öffnet sich in einem neuen Fenster\"><i class=\"icon-doc\"></i>18/4963</a>"
                ],
                "documents": [
                  "http://dip21.bundestag.de/dip21/btd/18/027/1802737.pdf",
                  "http://dip21.bundestag.de/dip21/btd/18/049/1804963.pdf"
                ],
                "isVote": true
              }
            ],
            "status": []
          },
          {
            "time": "2015-05-21T22:55:00.000Z",
            "top": "24 *",
            "heading": "Gesetz zum Internationalen Erbrecht",
            "topic": [
              {
                "lines": [
                  "Zweite und dritte Beratung des von der Bundesregierung",
                  "eingebrachten Entwurfs eines Gesetzes zum Internationalen Erbrecht und zur Änderung von Vorschriften zum Erbschein sowie zur Änderung sonstiger Vorschriften",
                  "Drucksache <a target='_blank' href=\"http://dip21.bundestag.de/dip21/btd/18/042/1804201.pdf\" class=\"dipLink\" title=\"Die PDF-Datei Drucksache 18/4201 öffnet sich in einem neuen Fenster\"><i class=\"icon-doc\"></i>18/4201</a>",
                  "Beschlussempfehlung und Bericht des Ausschusses für Recht und Verbraucherschutz (6. Ausschuss)",
                  "Drucksache <a target='_blank' href=\"http://dip21.bundestag.de/dip21/btd/18/049/1804961.pdf\" class=\"dipLink\" title=\"Die PDF-Datei Drucksache 18/4961 öffnet sich in einem neuen Fenster\"><i class=\"icon-doc\"></i>18/4961</a>"
                ],
                "documents": [
                  "http://dip21.bundestag.de/dip21/btd/18/042/1804201.pdf",
                  "http://dip21.bundestag.de/dip21/btd/18/049/1804961.pdf"
                ],
                "isVote": true
              }
            ],
            "status": []
          },
          {
            "time": "2015-05-21T23:00:00.000Z",
            "top": "25 *",
            "heading": "Anpassung der Abgabenordnung an den EU-Zollkodex",
            "topic": [
              {
                "lines": [
                  "Erste Beratung des von der Bundesregierung",
                  "eingebrachten Entwurfs eines Gesetzes zur Umsetzung der Protokollerklärung zum Gesetz zur Anpassung der Abgabenordnung an den Zollkodex der Union und zur Änderung weiterer steuerlicher Vorschriften",
                  "Drucksache <a target='_blank' href=\"http://dip21.bundestag.de/dip21/btd/18/049/1804902.pdf\" class=\"dipLink\" title=\"Die PDF-Datei Drucksache 18/4902 öffnet sich in einem neuen Fenster\"><i class=\"icon-doc\"></i>18/4902</a>"
                ],
                "documents": [
                  "http://dip21.bundestag.de/dip21/btd/18/049/1804902.pdf"
                ],
                "isVote": false
              }
            ],
            "status": []
          },
          {
            "time": "2015-05-21T23:00:00.000Z",
            "top": "",
            "heading": null,
            "topic": [
              {
                "lines": [
                  "Sitzungsende"
                ],
                "documents": [],
                "isVote": null
              }
            ],
            "status": []
          }
        ]
      },
      {
        "date": "2015-05-22T00:00:00.000Z",
        "dateText": "22. Mai 2015",
        "session": "107",
        "tops": [
          {
            "time": "2015-05-22T09:00:00.000Z",
            "top": "",
            "heading": null,
            "topic": [
              {
                "lines": [
                  "Sitzungseröffnung"
                ],
                "documents": [],
                "isVote": null
              }
            ],
            "status": []
          },
          {
            "time": "2015-05-22T09:00:00.000Z",
            "top": "27",
            "heading": "Gesetz zur Tarifeinheit",
            "topic": [
              {
                "lines": [
                  "a) Zweite und dritte Beratung des von der Bundesregierung",
                  "eingebrachten Entwurfs eines Gesetzes zur Tarifeinheit (Tarifeinheitsgesetz)",
                  "Drucksache <a target='_blank' href=\"http://dip21.bundestag.de/dip21/btd/18/040/1804062.pdf\" class=\"dipLink\" title=\"Die PDF-Datei Drucksache 18/4062 öffnet sich in einem neuen Fenster\"><i class=\"icon-doc\"></i>18/4062</a>",
                  "Beschlussempfehlung und Bericht des Ausschusses für Arbeit und Soziales (11. Ausschuss)",
                  "Drucksache <a target='_blank' href=\"http://dip21.bundestag.de/dip21/btd/18/049/1804966.pdf\" class=\"dipLink\" title=\"Die PDF-Datei Drucksache 18/4966 öffnet sich in einem neuen Fenster\"><i class=\"icon-doc\"></i>18/4966</a>"
                ],
                "documents": [
                  "http://dip21.bundestag.de/dip21/btd/18/040/1804062.pdf",
                  "http://dip21.bundestag.de/dip21/btd/18/049/1804966.pdf"
                ],
                "isVote": true
              },
              {
                "lines": [
                  "b) Beratung der Beschlussempfehlung und des Berichts des Ausschusses für Arbeit und Soziales (11. Ausschuss)",
                  "- zu dem Antrag der Fraktion DIE LINKE.",
                  "Tarifautonomie stärken – Streikrecht verteidigen",
                  "- zu dem Antrag der Fraktion BÜNDNIS 90/DIE GRÜNEN",
                  "Solidarität im Rahmen der Tarifpluralität ermöglichen – Tarifeinheit nicht gesetzlich regeln",
                  "Drucksachen <a target='_blank' href=\"http://dip21.bundestag.de/dip21/btd/18/041/1804184.pdf\" class=\"dipLink\" title=\"Die PDF-Datei Drucksache 18/4184 öffnet sich in einem neuen Fenster\"><i class=\"icon-doc\"></i>18/4184</a>, <a target='_blank' href=\"http://dip21.bundestag.de/dip21/btd/18/028/1802875.pdf\" class=\"dipLink\" title=\"Die PDF-Datei Drucksache 18/2875 öffnet sich in einem neuen Fenster\"><i class=\"icon-doc\"></i>18/2875</a>, <a target='_blank' href=\"http://dip21.bundestag.de/dip21/btd/18/049/1804966.pdf\" class=\"dipLink\" title=\"Die PDF-Datei Drucksache 18/4966 öffnet sich in einem neuen Fenster\"><i class=\"icon-doc\"></i>18/4966</a>"
                ],
                "documents": [
                  "http://dip21.bundestag.de/dip21/btd/18/041/1804184.pdf",
                  "http://dip21.bundestag.de/dip21/btd/18/028/1802875.pdf",
                  "http://dip21.bundestag.de/dip21/btd/18/049/1804966.pdf"
                ],
                "isVote": true
              }
            ],
            "status": []
          },
          {
            "time": "2015-05-22T10:25:00.000Z",
            "top": "28",
            "heading": "Bekämpfung von Doping im Sport",
            "topic": [
              {
                "lines": [
                  "Erste Beratung des von der Bundesregierung eingebrachten Entwurfs eines Gesetzes zur Bekämpfung von Doping im Sport",
                  "Drucksache <a target='_blank' href=\"http://dip21.bundestag.de/dip21/btd/18/048/1804898.pdf\" class=\"dipLink\" title=\"Die PDF-Datei Drucksache 18/4898 öffnet sich in einem neuen Fenster\"><i class=\"icon-doc\"></i>18/4898</a>"
                ],
                "documents": [
                  "http://dip21.bundestag.de/dip21/btd/18/048/1804898.pdf"
                ],
                "isVote": false
              }
            ],
            "status": []
          },
          {
            "time": "2015-05-22T12:20:00.000Z",
            "top": "29",
            "heading": "Verbesserung der Transparenz beim Scoring",
            "topic": [
              {
                "lines": [
                  "Erste Beratung des von der Fraktion BÜNDNIS 90/DIE GRÜNEN",
                  "eingebrachten Entwurfs eines Zweiten Gesetzes zur Änderung des Bundesdatenschutzgesetzes – Verbesserung der Transparenz und der Bedingungen beim Scoring (Scoringänderungsgesetz)",
                  "Drucksache <a target='_blank' href=\"http://dip21.bundestag.de/dip21/btd/18/048/1804864.pdf\" class=\"dipLink\" title=\"Die PDF-Datei Drucksache 18/4864 öffnet sich in einem neuen Fenster\"><i class=\"icon-doc\"></i>18/4864</a>"
                ],
                "documents": [
                  "http://dip21.bundestag.de/dip21/btd/18/048/1804864.pdf"
                ],
                "isVote": false
              }
            ],
            "status": []
          },
          {
            "time": "2015-05-22T13:05:00.000Z",
            "top": "30",
            "heading": "Wohngeldrecht und Wohnraumförderungsgesetz",
            "topic": [
              {
                "lines": [
                  "Erste Beratung des von der Bundesregierung",
                  "eingebrachten Entwurfs eines Gesetzes zur Reform des Wohngeldrechts und zur Änderung des Wohnraumförderungsgesetzes (WoGRefG)",
                  "Drucksache <a target='_blank' href=\"http://dip21.bundestag.de/dip21/btd/18/048/1804897.pdf\" class=\"dipLink\" title=\"Die PDF-Datei Drucksache 18/4897 öffnet sich in einem neuen Fenster\"><i class=\"icon-doc\"></i>18/4897</a> (neu)"
                ],
                "documents": [
                  "http://dip21.bundestag.de/dip21/btd/18/048/1804897.pdf"
                ],
                "isVote": false
              }
            ],
            "status": []
          },
          {
            "time": "2015-05-22T13:50:00.000Z",
            "top": "31",
            "heading": "Bericht über den Ausbau der Kindertagesbetreuung",
            "topic": [
              {
                "lines": [
                  "a) Beratung der Unterrichtung durch die Bundesregierung",
                  "Bericht der Bundesregierung über den Stand des Ausbaus der Kindertagesbetreuung für Kinder unter drei Jahren für das Berichtsjahr 2014 und Bilanzierung des Ausbaus durch das Kinderförderungsgesetz (Fünfter Bericht zur Evaluation des Kinderförderungsgesetzes)",
                  "Drucksache <a target='_blank' href=\"http://dip21.bundestag.de/dip21/btd/18/042/1804268.pdf\" class=\"dipLink\" title=\"Die PDF-Datei Drucksache 18/4268 öffnet sich in einem neuen Fenster\"><i class=\"icon-doc\"></i>18/4268</a>"
                ],
                "documents": [
                  "http://dip21.bundestag.de/dip21/btd/18/042/1804268.pdf"
                ],
                "isVote": null
              },
              {
                "lines": [
                  "b) Beratung der Beschlussempfehlung und des Berichts des Ausschusses für Familie, Senioren, Frauen und Jugend (13. Ausschuss)",
                  "- zu dem Antrag der Fraktion DIE LINKE.",
                  "Ausbau und Qualität in der Kinderbetreuung vorantreiben",
                  "- zu dem Antrag der Fraktion BÜNDNIS 90/DIE GRÜNEN",
                  "Qualität in der frühkindlichen Bildung fördern",
                  "Drucksachen <a target='_blank' href=\"http://dip21.bundestag.de/dip21/btd/18/026/1802605.pdf\" class=\"dipLink\" title=\"Die PDF-Datei Drucksache 18/2605 öffnet sich in einem neuen Fenster\"><i class=\"icon-doc\"></i>18/2605</a>, <a target='_blank' href=\"http://dip21.bundestag.de/dip21/btd/18/014/1801459.pdf\" class=\"dipLink\" title=\"Die PDF-Datei Drucksache 18/1459 öffnet sich in einem neuen Fenster\"><i class=\"icon-doc\"></i>18/1459</a>, <a target='_blank' href=\"http://dip21.bundestag.de/dip21/btd/18/043/1804368.pdf\" class=\"dipLink\" title=\"Die PDF-Datei Drucksache 18/4368 öffnet sich in einem neuen Fenster\"><i class=\"icon-doc\"></i>18/4368</a>"
                ],
                "documents": [
                  "http://dip21.bundestag.de/dip21/btd/18/026/1802605.pdf",
                  "http://dip21.bundestag.de/dip21/btd/18/014/1801459.pdf",
                  "http://dip21.bundestag.de/dip21/btd/18/043/1804368.pdf"
                ],
                "isVote": true
              }
            ],
            "status": []
          },
          {
            "time": "2015-05-22T14:40:00.000Z",
            "top": "32",
            "heading": "Bekämpfung von Langzeitarbeitslosigkeit",
            "topic": [
              {
                "lines": [
                  "Beratung der Beschlussempfehlung und des Berichts des Ausschusses für Arbeit und Soziales (11. Ausschuss)",
                  "zu dem Antrag der Fraktion DIE LINKE.",
                  "Fünf-Punkte-Programm zur Bekämpfung und Vermeidung von Langzeiterwerbslosigkeit",
                  "Drucksachen <a target='_blank' href=\"http://dip21.bundestag.de/dip21/btd/18/031/1803146.pdf\" class=\"dipLink\" title=\"Die PDF-Datei Drucksache 18/3146 öffnet sich in einem neuen Fenster\"><i class=\"icon-doc\"></i>18/3146</a>, <a target='_blank' href=\"http://dip21.bundestag.de/dip21/btd/18/049/1804967.pdf\" class=\"dipLink\" title=\"Die PDF-Datei Drucksache 18/4967 öffnet sich in einem neuen Fenster\"><i class=\"icon-doc\"></i>18/4967</a>"
                ],
                "documents": [
                  "http://dip21.bundestag.de/dip21/btd/18/031/1803146.pdf",
                  "http://dip21.bundestag.de/dip21/btd/18/049/1804967.pdf"
                ],
                "isVote": true
              }
            ],
            "status": []
          },
          {
            "time": "2015-05-22T15:20:00.000Z",
            "top": "ZP 7",
            "heading": "Aktuelle Stunde zu Klimaschutzziele im Bereich alter Kohlekraftwerke",
            "topic": [
              {
                "lines": [
                  "Aktuelle Stunde",
                  "auf Verlangen der Fraktion BÜNDNIS 90/DIE GRÜNEN",
                  "Haltung der Bundesregierung zur Änderung der Klimaschutzziele im Bereich alter Kohlekraftwerke"
                ],
                "documents": [],
                "isVote": null
              }
            ],
            "status": []
          },
          {
            "time": "2015-05-22T16:40:00.000Z",
            "top": "",
            "heading": null,
            "topic": [
              {
                "lines": [
                  "Sitzungsende"
                ],
                "documents": [],
                "isVote": null
              }
            ],
            "status": []
          }
        ]
      }
    ]
  }
}