{
  "meta": {
    "url": "https://www.bundestag.de/apps/plenar/plenar/conferenceweekDetail.form?limit=1&year=2018&week=47",
    "currentYear": 2018,
    "currentWeek": 47
  },
  "data": {
    "id": "2018_47",
    "previous": {
      "year": 2018,
      "week": 45
    },
    "this": {
      "year": 2018,
      "week": 47
    },
    "next": {
      "year": 2018,
      "week": 48
    },
    "sessions": [
      {
        "date": "2018-11-20T00:00:00.000Z",
        "dateText": "20. November 2018",
        "session": "63",
        "tops": [
          {
            "time": "2018-11-20T10:00:00.000Z",
            "top": "I",
            "heading": "Haushaltsgesetz 2019",
            "article": null,
            "topic": [
              {
                "lines": [
                  "a) Zweite Beratung des von der Bundesregierung eingebrachten Entwurfs eines Gesetzes über die Feststellung des Bundeshaushaltsplans für das Haushaltsjahr 2019 (Haushaltsgesetz 2019)",
                  "Drucksachen <a target='_blank' href=\"http://dip21.bundestag.de/dip21/btd/19/034/1903400.pdf\" class=\"dipLink\" title=\"Die PDF-Datei Drucksache 19/3400 öffnet sich in einem neuen Fenster\"><i class=\"icon-doc\"></i>19/3400</a>, <a target='_blank' href=\"http://dip21.bundestag.de/dip21/btd/19/034/1903402.pdf\" class=\"dipLink\" title=\"Die PDF-Datei Drucksache 19/3402 öffnet sich in einem neuen Fenster\"><i class=\"icon-doc\"></i>19/3402</a>"
                ],
                "documents": [
                  "http://dip21.bundestag.de/dip21/btd/19/034/1903400.pdf",
                  "http://dip21.bundestag.de/dip21/btd/19/034/1903402.pdf"
                ]
              },
              {
                "lines": [
                  "b) Beratung der Beschlussempfehlung des Haushaltsausschusses (8. Ausschuss) zu der Unterrichtung durch die Bundesregierung",
                  "Finanzplan des Bundes 2018 bis 2022",
                  "Drucksachen <a target='_blank' href=\"http://dip21.bundestag.de/dip21/btd/19/034/1903401.pdf\" class=\"dipLink\" title=\"Die PDF-Datei Drucksache 19/3401 öffnet sich in einem neuen Fenster\"><i class=\"icon-doc\"></i>19/3401</a>, <a target='_blank' href=\"http://dip21.bundestag.de/dip21/btd/19/034/1903402.pdf\" class=\"dipLink\" title=\"Die PDF-Datei Drucksache 19/3402 öffnet sich in einem neuen Fenster\"><i class=\"icon-doc\"></i>19/3402</a>, <a target='_blank' href=\"http://dip21.bundestag.de/dip21/btd/19/046/1904627.pdf\" class=\"dipLink\" title=\"Die PDF-Datei Drucksache 19/4627 öffnet sich in einem neuen Fenster\"><i class=\"icon-doc\"></i>19/4627</a>"
                ],
                "documents": [
                  "http://dip21.bundestag.de/dip21/btd/19/034/1903401.pdf",
                  "http://dip21.bundestag.de/dip21/btd/19/034/1903402.pdf",
                  "http://dip21.bundestag.de/dip21/btd/19/046/1904627.pdf"
                ]
              }
            ],
            "status": [
              {
                "line": "beendet",
                "documents": []
              }
            ]
          },
          {
            "time": "2018-11-20T10:00:00.000Z",
            "top": "I.4",
            "heading": "Finanzen, Bundesrechnungshof",
            "article": "https://www.bundestag.de/dokumente/textarchiv/2018/kw47-de-finanzen-bundesrechnungshof-576930",
            "topic": [
              {
                "lines": [
                  "a) Beschlussempfehlungen und Berichte des Haushaltsausschusses",
                  "(8. Ausschuss)",
                  "hier: Einzelplan 08",
                  "Bundesministerium der Finanzen",
                  "Drucksache <a target='_blank' href=\"http://dip21.bundestag.de/dip21/btd/19/046/1904608.pdf\" class=\"dipLink\" title=\"Die PDF-Datei Drucksache 19/4608 öffnet sich in einem neuen Fenster\"><i class=\"icon-doc\"></i>19/4608</a>, <a target='_blank' href=\"http://dip21.bundestag.de/dip21/btd/19/046/1904624.pdf\" class=\"dipLink\" title=\"Die PDF-Datei Drucksache 19/4624 öffnet sich in einem neuen Fenster\"><i class=\"icon-doc\"></i>19/4624</a>"
                ],
                "documents": [
                  "http://dip21.bundestag.de/dip21/btd/19/046/1904608.pdf",
                  "http://dip21.bundestag.de/dip21/btd/19/046/1904624.pdf"
                ]
              },
              {
                "lines": [
                  "b) Beschlussempfehlungen und Berichte des Haushaltsausschusses",
                  "(8. Ausschuss)",
                  "hier: Einzelplan 20",
                  "Bundesrechnungshof",
                  "Drucksache <a target='_blank' href=\"http://dip21.bundestag.de/dip21/btd/19/046/1904625.pdf\" class=\"dipLink\" title=\"Die PDF-Datei Drucksache 19/4625 öffnet sich in einem neuen Fenster\"><i class=\"icon-doc\"></i>19/4625</a>"
                ],
                "documents": [
                  "http://dip21.bundestag.de/dip21/btd/19/046/1904625.pdf"
                ]
              }
            ],
            "status": [
              {
                "line": "Einzelplan 08 (Beschlussempfehlung <a target='_blank' href=\"http://dip21.bundestag.de/dip21/btd/19/046/1904608.pdf\" class=\"dipLink\" title=\"Die PDF-Datei Drucksache 19/4608 öffnet sich in einem neuen Fenster\"><i class=\"icon-doc\"></i>19/4608</a> und <a target='_blank' href=\"http://dip21.bundestag.de/dip21/btd/19/046/1904624.pdf\" class=\"dipLink\" title=\"Die PDF-Datei Drucksache 19/4624 öffnet sich in einem neuen Fenster\"><i class=\"icon-doc\"></i>19/4624</a>) in der Ausschussfassung angenommen",
                "documents": [
                  "http://dip21.bundestag.de/dip21/btd/19/046/1904608.pdf",
                  "http://dip21.bundestag.de/dip21/btd/19/046/1904624.pdf"
                ]
              },
              {
                "line": "Einzelplan 20 (Beschlussempfehlung <a target='_blank' href=\"http://dip21.bundestag.de/dip21/btd/19/046/1904625.pdf\" class=\"dipLink\" title=\"Die PDF-Datei Drucksache 19/4625 öffnet sich in einem neuen Fenster\"><i class=\"icon-doc\"></i>19/4625</a>) angenommen",
                "documents": [
                  "http://dip21.bundestag.de/dip21/btd/19/046/1904625.pdf"
                ]
              }
            ]
          },
          {
            "time": "2018-11-20T11:45:00.000Z",
            "top": "I.6",
            "heading": "Umwelt, Naturschutz und nukleare Sicherheit",
            "article": "https://www.bundestag.de/dokumente/textarchiv/2018/kw47-de-umwelt-naturschutz-nukleare-sicherheit-576934",
            "topic": [
              {
                "lines": [
                  "Beschlussempfehlungen und Berichte des Haushaltsausschusses",
                  "(8. Ausschuss)",
                  "hier: Einzelplan 16",
                  "Bundesministerium für Umwelt, Naturschutz",
                  "und nukleare Sicherheit",
                  "Drucksache <a target='_blank' href=\"http://dip21.bundestag.de/dip21/btd/19/046/1904624.pdf\" class=\"dipLink\" title=\"Die PDF-Datei Drucksache 19/4624 öffnet sich in einem neuen Fenster\"><i class=\"icon-doc\"></i>19/4624</a>, <a target='_blank' href=\"http://dip21.bundestag.de/dip21/btd/19/046/1904625.pdf\" class=\"dipLink\" title=\"Die PDF-Datei Drucksache 19/4625 öffnet sich in einem neuen Fenster\"><i class=\"icon-doc\"></i>19/4625</a>"
                ],
                "documents": [
                  "http://dip21.bundestag.de/dip21/btd/19/046/1904624.pdf",
                  "http://dip21.bundestag.de/dip21/btd/19/046/1904625.pdf"
                ]
              }
            ],
            "status": [
              {
                "line": "Einzelplan 16 (Beschlussempfehlung <a target='_blank' href=\"http://dip21.bundestag.de/dip21/btd/19/046/1904624.pdf\" class=\"dipLink\" title=\"Die PDF-Datei Drucksache 19/4624 öffnet sich in einem neuen Fenster\"><i class=\"icon-doc\"></i>19/4624</a> und <a target='_blank' href=\"http://dip21.bundestag.de/dip21/btd/19/046/1904625.pdf\" class=\"dipLink\" title=\"Die PDF-Datei Drucksache 19/4625 öffnet sich in einem neuen Fenster\"><i class=\"icon-doc\"></i>19/4625</a>) in der Ausschussfassung angenommen",
                "documents": [
                  "http://dip21.bundestag.de/dip21/btd/19/046/1904624.pdf",
                  "http://dip21.bundestag.de/dip21/btd/19/046/1904625.pdf"
                ]
              }
            ]
          },
          {
            "time": "2018-11-20T15:10:00.000Z",
            "top": "I.8",
            "heading": "Ernährung und Landwirtschaft",
            "article": "https://www.bundestag.de/dokumente/textarchiv/2018/kw47-de-ernaehrung-landwirtschaft-576956",
            "topic": [
              {
                "lines": [
                  "Beschlussempfehlungen und Berichte des Haushaltsausschusses",
                  "(8. Ausschuss)",
                  "hier: Einzelplan 10",
                  "Bundesministerium für Ernährung und Landwirtschaft",
                  "Drucksache <a target='_blank' href=\"http://dip21.bundestag.de/dip21/btd/19/046/1904624.pdf\" class=\"dipLink\" title=\"Die PDF-Datei Drucksache 19/4624 öffnet sich in einem neuen Fenster\"><i class=\"icon-doc\"></i>19/4624</a>, <a target='_blank' href=\"http://dip21.bundestag.de/dip21/btd/19/046/1904625.pdf\" class=\"dipLink\" title=\"Die PDF-Datei Drucksache 19/4625 öffnet sich in einem neuen Fenster\"><i class=\"icon-doc\"></i>19/4625</a>"
                ],
                "documents": [
                  "http://dip21.bundestag.de/dip21/btd/19/046/1904624.pdf",
                  "http://dip21.bundestag.de/dip21/btd/19/046/1904625.pdf"
                ]
              }
            ],
            "status": [
              {
                "line": "Einzelplan 10 (Beschlussempfehlung <a target='_blank' href=\"http://dip21.bundestag.de/dip21/btd/19/046/1904624.pdf\" class=\"dipLink\" title=\"Die PDF-Datei Drucksache 19/4624 öffnet sich in einem neuen Fenster\"><i class=\"icon-doc\"></i>19/4624</a> und <a target='_blank' href=\"http://dip21.bundestag.de/dip21/btd/19/046/1904625.pdf\" class=\"dipLink\" title=\"Die PDF-Datei Drucksache 19/4625 öffnet sich in einem neuen Fenster\"><i class=\"icon-doc\"></i>19/4625</a>) in der Ausschussfassung angenommen",
                "documents": [
                  "http://dip21.bundestag.de/dip21/btd/19/046/1904624.pdf",
                  "http://dip21.bundestag.de/dip21/btd/19/046/1904625.pdf"
                ]
              }
            ]
          }
        ]
      },
      {
        "date": "2018-11-21T00:00:00.000Z",
        "dateText": "21. November 2018",
        "session": "64",
        "tops": [
          {
            "time": "2018-11-21T09:00:00.000Z",
            "top": "I.9",
            "heading": "Bundeskanzlerin und Bundeskanzleramt",
            "article": "https://www.bundestag.de/dokumente/textarchiv/2018/kw47-de-bundeskanzleramt-576942",
            "topic": [
              {
                "lines": [
                  "Beschlussempfehlungen und Berichte des Haushaltsausschusses",
                  "(8. Ausschuss)",
                  "hier: Einzelplan 04",
                  "Bundeskanzlerin und Bundeskanzleramt",
                  "Drucksache <a target='_blank' href=\"http://dip21.bundestag.de/dip21/btd/19/046/1904624.pdf\" class=\"dipLink\" title=\"Die PDF-Datei Drucksache 19/4624 öffnet sich in einem neuen Fenster\"><i class=\"icon-doc\"></i>19/4624</a>, <a target='_blank' href=\"http://dip21.bundestag.de/dip21/btd/19/046/1904625.pdf\" class=\"dipLink\" title=\"Die PDF-Datei Drucksache 19/4625 öffnet sich in einem neuen Fenster\"><i class=\"icon-doc\"></i>19/4625</a>"
                ],
                "documents": [
                  "http://dip21.bundestag.de/dip21/btd/19/046/1904624.pdf",
                  "http://dip21.bundestag.de/dip21/btd/19/046/1904625.pdf"
                ]
              },
              {
                "lines": [
                  "Namentliche Abstimmung"
                ],
                "documents": []
              }
            ],
            "status": [
              {
                "line": "namentliche Abstimmung über Einzelplan 04 (Beschlussempfehlung <a target='_blank' href=\"http://dip21.bundestag.de/dip21/btd/19/046/1904624.pdf\" class=\"dipLink\" title=\"Die PDF-Datei Drucksache 19/4624 öffnet sich in einem neuen Fenster\"><i class=\"icon-doc\"></i>19/4624</a> und <a target='_blank' href=\"http://dip21.bundestag.de/dip21/btd/19/046/1904625.pdf\" class=\"dipLink\" title=\"Die PDF-Datei Drucksache 19/4625 öffnet sich in einem neuen Fenster\"><i class=\"icon-doc\"></i>19/4625</a>) in der Ausschussfassung",
                "documents": [
                  "http://dip21.bundestag.de/dip21/btd/19/046/1904624.pdf",
                  "http://dip21.bundestag.de/dip21/btd/19/046/1904625.pdf"
                ]
              },
              {
                "line": "12:49:37: Beginn der namentlichen Abstimmung",
                "documents": []
              },
              {
                "line": "12:53:08: Ende der namentlichen Abstimmung",
                "documents": []
              },
              {
                "line": "Gesamt: 657 Ja: 382 Nein: 275 Enthaltungen: 0",
                "documents": []
              },
              {
                "line": "Einzelplan 04 (Beschlussempfehlung <a target='_blank' href=\"http://dip21.bundestag.de/dip21/btd/19/046/1904624.pdf\" class=\"dipLink\" title=\"Die PDF-Datei Drucksache 19/4624 öffnet sich in einem neuen Fenster\"><i class=\"icon-doc\"></i>19/4624</a> und <a target='_blank' href=\"http://dip21.bundestag.de/dip21/btd/19/046/1904625.pdf\" class=\"dipLink\" title=\"Die PDF-Datei Drucksache 19/4625 öffnet sich in einem neuen Fenster\"><i class=\"icon-doc\"></i>19/4625</a>) in der Ausschussfassung angenommen",
                "documents": [
                  "http://dip21.bundestag.de/dip21/btd/19/046/1904624.pdf",
                  "http://dip21.bundestag.de/dip21/btd/19/046/1904625.pdf"
                ]
              }
            ]
          },
          {
            "time": "2018-11-21T12:55:00.000Z",
            "top": "I.11",
            "heading": "Verteidigung",
            "article": "https://www.bundestag.de/dokumente/textarchiv/2018/kw47-de-verteidigung-576946",
            "topic": [
              {
                "lines": [
                  "Beschlussempfehlungen und Berichte des Haushaltsausschusses",
                  "(8. Ausschuss)",
                  "hier: Einzelplan 14",
                  "Bundesministerium der Verteidigung",
                  "Drucksache <a target='_blank' href=\"http://dip21.bundestag.de/dip21/btd/19/046/1904613.pdf\" class=\"dipLink\" title=\"Die PDF-Datei Drucksache 19/4613 öffnet sich in einem neuen Fenster\"><i class=\"icon-doc\"></i>19/4613</a>, <a target='_blank' href=\"http://dip21.bundestag.de/dip21/btd/19/046/1904624.pdf\" class=\"dipLink\" title=\"Die PDF-Datei Drucksache 19/4624 öffnet sich in einem neuen Fenster\"><i class=\"icon-doc\"></i>19/4624</a>"
                ],
                "documents": [
                  "http://dip21.bundestag.de/dip21/btd/19/046/1904613.pdf",
                  "http://dip21.bundestag.de/dip21/btd/19/046/1904624.pdf"
                ]
              }
            ],
            "status": [
              {
                "line": "Einzelplan 14 (Beschlussempfehlung <a target='_blank' href=\"http://dip21.bundestag.de/dip21/btd/19/046/1904613.pdf\" class=\"dipLink\" title=\"Die PDF-Datei Drucksache 19/4613 öffnet sich in einem neuen Fenster\"><i class=\"icon-doc\"></i>19/4613</a> und <a target='_blank' href=\"http://dip21.bundestag.de/dip21/btd/19/046/1904624.pdf\" class=\"dipLink\" title=\"Die PDF-Datei Drucksache 19/4624 öffnet sich in einem neuen Fenster\"><i class=\"icon-doc\"></i>19/4624</a>) in der Ausschussfassung angenommen",
                "documents": [
                  "http://dip21.bundestag.de/dip21/btd/19/046/1904613.pdf",
                  "http://dip21.bundestag.de/dip21/btd/19/046/1904624.pdf"
                ]
              }
            ]
          },
          {
            "time": "2018-11-21T16:30:00.000Z",
            "top": "",
            "heading": null,
            "article": null,
            "topic": [
              {
                "lines": [
                  "Sitzungsende"
                ],
                "documents": []
              }
            ],
            "status": [
              {
                "line": "nächste Sitzung Donnerstag, 22. November 2018, 9 Uhr",
                "documents": []
              }
            ]
          }
        ]
      },
      {
        "date": "2018-11-22T00:00:00.000Z",
        "dateText": "22. November 2018",
        "session": "65",
        "tops": [
          {
            "time": "2018-11-22T09:00:00.000Z",
            "top": "I.13",
            "heading": "Gesundheit",
            "article": "https://www.bundestag.de/dokumente/textarchiv/2018/kw47-de-gesundheit-576940",
            "topic": [
              {
                "lines": [
                  "Beschlussempfehlungen und Berichte des Haushaltsausschusses",
                  "(8. Ausschuss)",
                  "hier: Einzelplan 15",
                  "Bundesministerium für Gesundheit",
                  "Drucksachen <a target='_blank' href=\"http://dip21.bundestag.de/dip21/btd/19/046/1904624.pdf\" class=\"dipLink\" title=\"Die PDF-Datei Drucksache 19/4624 öffnet sich in einem neuen Fenster\"><i class=\"icon-doc\"></i>19/4624</a>, <a target='_blank' href=\"http://dip21.bundestag.de/dip21/btd/19/046/1904625.pdf\" class=\"dipLink\" title=\"Die PDF-Datei Drucksache 19/4625 öffnet sich in einem neuen Fenster\"><i class=\"icon-doc\"></i>19/4625</a>"
                ],
                "documents": [
                  "http://dip21.bundestag.de/dip21/btd/19/046/1904624.pdf",
                  "http://dip21.bundestag.de/dip21/btd/19/046/1904625.pdf"
                ]
              }
            ],
            "status": [
              {
                "line": "Einzelplan 15 (Beschlussempfehlung <a target='_blank' href=\"http://dip21.bundestag.de/dip21/btd/19/046/1904624.pdf\" class=\"dipLink\" title=\"Die PDF-Datei Drucksache 19/4624 öffnet sich in einem neuen Fenster\"><i class=\"icon-doc\"></i>19/4624</a> und <a target='_blank' href=\"http://dip21.bundestag.de/dip21/btd/19/046/1904625.pdf\" class=\"dipLink\" title=\"Die PDF-Datei Drucksache 19/4625 öffnet sich in einem neuen Fenster\"><i class=\"icon-doc\"></i>19/4625</a>) in der Ausschussfassung angenommen",
                "documents": [
                  "http://dip21.bundestag.de/dip21/btd/19/046/1904624.pdf",
                  "http://dip21.bundestag.de/dip21/btd/19/046/1904625.pdf"
                ]
              }
            ]
          },
          {
            "time": "2018-11-22T10:50:00.000Z",
            "top": "ZP 1",
            "heading": "Wahl eines Richters des Bundesverfassungsgerichts",
            "article": "https://www.bundestag.de/dokumente/textarchiv/2018/kw47-de-richterwahl-579312",
            "topic": [
              {
                "lines": [
                  "Wahlvorschlag des Wahlausschusses für die Richter des Bundesverfassungsgerichts",
                  "Wahl einer Richterin oder eines Richters des Bundesverfassungsgerichts",
                  "Drucksache <a target='_blank' href=\"http://dip21.bundestag.de/dip21/btd/19/058/1905861.pdf\" class=\"dipLink\" title=\"Die PDF-Datei Drucksache 19/5861 öffnet sich in einem neuen Fenster\"><i class=\"icon-doc\"></i>19/5861</a>"
                ],
                "documents": [
                  "http://dip21.bundestag.de/dip21/btd/19/058/1905861.pdf"
                ]
              },
              {
                "lines": [
                  "Geheime Wahl mit Stimmkarte und Wahlausweis"
                ],
                "documents": []
              }
            ],
            "status": [
              {
                "line": "Wahl eines Richters des BVerfG (Wahlvorschlag <a target='_blank' href=\"http://dip21.bundestag.de/dip21/btd/19/058/1905861.pdf\" class=\"dipLink\" title=\"Die PDF-Datei Drucksache 19/5861 öffnet sich in einem neuen Fenster\"><i class=\"icon-doc\"></i>19/5861</a>: Herr Dr. Stephan Harbarth)",
                "documents": [
                  "http://dip21.bundestag.de/dip21/btd/19/058/1905861.pdf"
                ]
              },
              {
                "line": "12:35:24: Beginn der Wahl",
                "documents": []
              },
              {
                "line": "12:57:07: Ende der Wahl",
                "documents": []
              },
              {
                "line": "Gesamt: 652 Ja: 452 Nein: 166 Enthaltungen: 34",
                "documents": []
              },
              {
                "line": "Wahlvorschlag angenommen",
                "documents": []
              }
            ]
          },
          {
            "time": "2018-11-22T12:55:00.000Z",
            "top": "IV., ZP 3",
            "heading": "Abschließende Beratungen ohne Aussprache",
            "article": "https://www.bundestag.de/dokumente/textarchiv/2018/kw47-de-abschliessende-beratungen-576970",
            "topic": [
              {
                "lines": [
                  "Abschließende Beratungen ohne Aussprache"
                ],
                "documents": []
              },
              {
                "lines": [
                  "a) Beratung des Antrags der Fraktion BÜNDNIS 90/DIE GRÜNEN",
                  "zu dem Vorschlag für eine Richtlinie des Europäischen Parlaments und des Rates über unlautere Handelspraktiken in den Geschäftsbeziehungen zwischen Unternehmen in der Lebensmittelversorgungskette KOM(2018) 173 endg.; Ratsdok 7809/18",
                  "hier: Stellungnahme gegenüber der Bundesregierung gemäß Artikel 23 Absatz 3 des Grundgesetzes",
                  "Kein Verbot besserer Tier- und Umweltschutzstandards im Handel",
                  "Drucksache <a target='_blank' href=\"http://dip21.bundestag.de/dip21/btd/19/058/1905891.pdf\" class=\"dipLink\" title=\"Die PDF-Datei Drucksache 19/5891 öffnet sich in einem neuen Fenster\"><i class=\"icon-doc\"></i>19/5891</a>"
                ],
                "documents": [
                  "http://dip21.bundestag.de/dip21/btd/19/058/1905891.pdf"
                ]
              },
              {
                "lines": [
                  "b) Beratung der Beschlussempfehlung des Petitionsausschusses",
                  "(2. Ausschuss)",
                  "Sammelübersicht 125 zu Petitionen",
                  "Drucksache <a target='_blank' href=\"http://dip21.bundestag.de/dip21/btd/19/055/1905566.pdf\" class=\"dipLink\" title=\"Die PDF-Datei Drucksache 19/5566 öffnet sich in einem neuen Fenster\"><i class=\"icon-doc\"></i>19/5566</a>"
                ],
                "documents": [
                  "http://dip21.bundestag.de/dip21/btd/19/055/1905566.pdf"
                ]
              },
              {
                "lines": [
                  "c) Beratung der Beschlussempfehlung des Petitionsausschusses",
                  "(2. Ausschuss)",
                  "Sammelübersicht 126 zu Petitionen",
                  "Drucksache <a target='_blank' href=\"http://dip21.bundestag.de/dip21/btd/19/055/1905567.pdf\" class=\"dipLink\" title=\"Die PDF-Datei Drucksache 19/5567 öffnet sich in einem neuen Fenster\"><i class=\"icon-doc\"></i>19/5567</a>"
                ],
                "documents": [
                  "http://dip21.bundestag.de/dip21/btd/19/055/1905567.pdf"
                ]
              },
              {
                "lines": [
                  "d) Beratung der Beschlussempfehlung des Petitionsausschusses",
                  "(2. Ausschuss)",
                  "Sammelübersicht 127 zu Petitionen",
                  "Drucksache <a target='_blank' href=\"http://dip21.bundestag.de/dip21/btd/19/055/1905568.pdf\" class=\"dipLink\" title=\"Die PDF-Datei Drucksache 19/5568 öffnet sich in einem neuen Fenster\"><i class=\"icon-doc\"></i>19/5568</a>"
                ],
                "documents": [
                  "http://dip21.bundestag.de/dip21/btd/19/055/1905568.pdf"
                ]
              },
              {
                "lines": [
                  "e) Beratung der Beschlussempfehlung des Petitionsausschusses",
                  "(2. Ausschuss)",
                  "Sammelübersicht 128 zu Petitionen",
                  "Drucksache <a target='_blank' href=\"http://dip21.bundestag.de/dip21/btd/19/055/1905569.pdf\" class=\"dipLink\" title=\"Die PDF-Datei Drucksache 19/5569 öffnet sich in einem neuen Fenster\"><i class=\"icon-doc\"></i>19/5569</a>"
                ],
                "documents": [
                  "http://dip21.bundestag.de/dip21/btd/19/055/1905569.pdf"
                ]
              },
              {
                "lines": [
                  "f) Beratung der Beschlussempfehlung des Petitionsausschusses",
                  "(2. Ausschuss)",
                  "Sammelübersicht 129 zu Petitionen",
                  "Drucksache <a target='_blank' href=\"http://dip21.bundestag.de/dip21/btd/19/055/1905570.pdf\" class=\"dipLink\" title=\"Die PDF-Datei Drucksache 19/5570 öffnet sich in einem neuen Fenster\"><i class=\"icon-doc\"></i>19/5570</a>"
                ],
                "documents": [
                  "http://dip21.bundestag.de/dip21/btd/19/055/1905570.pdf"
                ]
              },
              {
                "lines": [
                  "g) Beratung der Beschlussempfehlung des Petitionsausschusses",
                  "(2. Ausschuss)",
                  "Sammelübersicht 130 zu Petitionen",
                  "Drucksache <a target='_blank' href=\"http://dip21.bundestag.de/dip21/btd/19/055/1905571.pdf\" class=\"dipLink\" title=\"Die PDF-Datei Drucksache 19/5571 öffnet sich in einem neuen Fenster\"><i class=\"icon-doc\"></i>19/5571</a>"
                ],
                "documents": [
                  "http://dip21.bundestag.de/dip21/btd/19/055/1905571.pdf"
                ]
              },
              {
                "lines": [
                  "h) Beratung der Beschlussempfehlung des Petitionsausschusses",
                  "(2. Ausschuss)",
                  "Sammelübersicht 131 zu Petitionen",
                  "Drucksache <a target='_blank' href=\"http://dip21.bundestag.de/dip21/btd/19/055/1905572.pdf\" class=\"dipLink\" title=\"Die PDF-Datei Drucksache 19/5572 öffnet sich in einem neuen Fenster\"><i class=\"icon-doc\"></i>19/5572</a>"
                ],
                "documents": [
                  "http://dip21.bundestag.de/dip21/btd/19/055/1905572.pdf"
                ]
              },
              {
                "lines": [
                  "i) Beratung der Beschlussempfehlung des Petitionsausschusses",
                  "(2. Ausschuss)",
                  "Sammelübersicht 132 zu Petitionen",
                  "Drucksache <a target='_blank' href=\"http://dip21.bundestag.de/dip21/btd/19/055/1905573.pdf\" class=\"dipLink\" title=\"Die PDF-Datei Drucksache 19/5573 öffnet sich in einem neuen Fenster\"><i class=\"icon-doc\"></i>19/5573</a>"
                ],
                "documents": [
                  "http://dip21.bundestag.de/dip21/btd/19/055/1905573.pdf"
                ]
              },
              {
                "lines": [
                  "j) Beratung der Beschlussempfehlung des Petitionsausschusses",
                  "(2. Ausschuss)",
                  "Sammelübersicht 133 zu Petitionen",
                  "Drucksache <a target='_blank' href=\"http://dip21.bundestag.de/dip21/btd/19/055/1905574.pdf\" class=\"dipLink\" title=\"Die PDF-Datei Drucksache 19/5574 öffnet sich in einem neuen Fenster\"><i class=\"icon-doc\"></i>19/5574</a>"
                ],
                "documents": [
                  "http://dip21.bundestag.de/dip21/btd/19/055/1905574.pdf"
                ]
              },
              {
                "lines": [
                  "k) Beratung der Beschlussempfehlung des Petitionsausschusses",
                  "(2. Ausschuss)",
                  "Sammelübersicht 134 zu Petitionen",
                  "Drucksache <a target='_blank' href=\"http://dip21.bundestag.de/dip21/btd/19/055/1905575.pdf\" class=\"dipLink\" title=\"Die PDF-Datei Drucksache 19/5575 öffnet sich in einem neuen Fenster\"><i class=\"icon-doc\"></i>19/5575</a>"
                ],
                "documents": [
                  "http://dip21.bundestag.de/dip21/btd/19/055/1905575.pdf"
                ]
              },
              {
                "lines": [
                  "l) Beratung der Beschlussempfehlung des Petitionsausschusses",
                  "(2. Ausschuss)",
                  "Sammelübersicht 135 zu Petitionen",
                  "Drucksache <a target='_blank' href=\"http://dip21.bundestag.de/dip21/btd/19/055/1905576.pdf\" class=\"dipLink\" title=\"Die PDF-Datei Drucksache 19/5576 öffnet sich in einem neuen Fenster\"><i class=\"icon-doc\"></i>19/5576</a>"
                ],
                "documents": [
                  "http://dip21.bundestag.de/dip21/btd/19/055/1905576.pdf"
                ]
              },
              {
                "lines": [
                  "m) Beratung der Beschlussempfehlung des Petitionsausschusses",
                  "(2. Ausschuss)",
                  "Sammelübersicht 136 zu Petitionen",
                  "Drucksache <a target='_blank' href=\"http://dip21.bundestag.de/dip21/btd/19/055/1905577.pdf\" class=\"dipLink\" title=\"Die PDF-Datei Drucksache 19/5577 öffnet sich in einem neuen Fenster\"><i class=\"icon-doc\"></i>19/5577</a>"
                ],
                "documents": [
                  "http://dip21.bundestag.de/dip21/btd/19/055/1905577.pdf"
                ]
              },
              {
                "lines": [
                  "ZP 3) Weitere abschließende Beratungen ohne Aussprache"
                ],
                "documents": []
              },
              {
                "lines": [
                  "a) Zweite und dritte Beratung des von der Bundesregierung eingebrachten Entwurfs eines Gesetzes zur Neuordnung des Tierzuchtrechts",
                  "Drucksachen <a target='_blank' href=\"http://dip21.bundestag.de/dip21/btd/19/049/1904950.pdf\" class=\"dipLink\" title=\"Die PDF-Datei Drucksache 19/4950 öffnet sich in einem neuen Fenster\"><i class=\"icon-doc\"></i>19/4950</a>, <a target='_blank' href=\"http://dip21.bundestag.de/dip21/btd/19/054/1905420.pdf\" class=\"dipLink\" title=\"Die PDF-Datei Drucksache 19/5420 öffnet sich in einem neuen Fenster\"><i class=\"icon-doc\"></i>19/5420</a>, <a target='_blank' href=\"http://dip21.bundestag.de/dip21/btd/19/056/1905647.pdf\" class=\"dipLink\" title=\"Die PDF-Datei Drucksache 19/5647 öffnet sich in einem neuen Fenster\"><i class=\"icon-doc\"></i>19/5647</a> Nr. 18",
                  "Beschlussempfehlung und Bericht des Ausschusses für Ernährung und Landwirtschaft (10. Ausschuss)",
                  "Drucksache <a target='_blank' href=\"http://dip21.bundestag.de/dip21/btd/19/056/1905682.pdf\" class=\"dipLink\" title=\"Die PDF-Datei Drucksache 19/5682 öffnet sich in einem neuen Fenster\"><i class=\"icon-doc\"></i>19/5682</a>"
                ],
                "documents": [
                  "http://dip21.bundestag.de/dip21/btd/19/049/1904950.pdf",
                  "http://dip21.bundestag.de/dip21/btd/19/054/1905420.pdf",
                  "http://dip21.bundestag.de/dip21/btd/19/056/1905647.pdf",
                  "http://dip21.bundestag.de/dip21/btd/19/056/1905682.pdf"
                ]
              },
              {
                "lines": [
                  "b) Beratung des Antrags der Fraktion der AfD",
                  "zu dem geänderten Vorschlag für eine Verordnung des Europäischen Parlaments und des Rates zur Änderung der Verordnung (EU) Nr. 1093/2010 zur Errichtung einer Europäischen Aufsichtsbehörde (Europäische Bankenaufsichtsbehörde), der Verordnung (EU) Nr. 1094/2010 zur Errichtung einer Europäischen Aufsichtsbehörde (Europäische Aufsichtsbehörde für das Versicherungswesen und die betriebliche Altersversorgung), der Verordnung (EU) Nr. 1095/2010 zur Errichtung einer Europäischen Aufsichtsbehörde (Europäische Wertpapier- und Marktaufsichtsbehörde), der Verordnung (EU) Nr. 345/2013 über Europäische Risikokapitalfonds, der Verordnung (EU) Nr. 346/2013 über Europäische Fonds für soziales Unternehmertum, der Verordnung (EU) Nr. 600/2014 über Märkte für Finanzinstrumente, der Verordnung (EU) 2015/760 über europäische langfristige Investmentfonds, der Verordnung (EU) 2016/1011 über Indizes, die bei Finanzinstrumenten und Finanzkontrakten als Referenzwert oder zur Messung der Wertentwicklung eines Investmentfonds verwendet werden, der Verordnung (EU) 2017/1129 über den Prospekt, der beim öffentlichen Angebot von Wertpapieren oder bei deren Zulassung zum Handel an einem geregelten Markt zu veröffentlichen ist, und der Richtlinie (EU) 2015/849 zur Verhinderung der Nutzung des Finanzsystems zum Zwecke der Geldwäsche und der Terrorismusfinanzierung",
                  "KOM(2018) 646 endg.; Ratsdok. 12111/18",
                  "hier:\tBegründete Stellungnahme gemäß Artikel 6 des Protokolls Nr. 2 zum Vertrag von Lissabon (Prüfung der Grundsätze der Subsidiarität und der Verhältnismäßigkeit)",
                  "Unvereinbarkeit der Verordnungsentwürfe mit den Rechtsgrundlagen der Europäischen Union",
                  "Drucksache <a target='_blank' href=\"http://dip21.bundestag.de/dip21/btd/19/059/1905910.pdf\" class=\"dipLink\" title=\"Die PDF-Datei Drucksache 19/5910 öffnet sich in einem neuen Fenster\"><i class=\"icon-doc\"></i>19/5910</a>"
                ],
                "documents": [
                  "http://dip21.bundestag.de/dip21/btd/19/059/1905910.pdf"
                ]
              }
            ],
            "status": [
              {
                "line": "Antrag <a target='_blank' href=\"http://dip21.bundestag.de/dip21/btd/19/058/1905891.pdf\" class=\"dipLink\" title=\"Die PDF-Datei Drucksache 19/5891 öffnet sich in einem neuen Fenster\"><i class=\"icon-doc\"></i>19/5891</a> abgelehnt",
                "documents": [
                  "http://dip21.bundestag.de/dip21/btd/19/058/1905891.pdf"
                ]
              },
              {
                "line": "Sammelübersicht 125 auf <a target='_blank' href=\"http://dip21.bundestag.de/dip21/btd/19/055/1905566.pdf\" class=\"dipLink\" title=\"Die PDF-Datei Drucksache 19/5566 öffnet sich in einem neuen Fenster\"><i class=\"icon-doc\"></i>19/5566</a> angenommen",
                "documents": [
                  "http://dip21.bundestag.de/dip21/btd/19/055/1905566.pdf"
                ]
              },
              {
                "line": "Sammelübersicht 126 auf <a target='_blank' href=\"http://dip21.bundestag.de/dip21/btd/19/055/1905567.pdf\" class=\"dipLink\" title=\"Die PDF-Datei Drucksache 19/5567 öffnet sich in einem neuen Fenster\"><i class=\"icon-doc\"></i>19/5567</a> angenommen",
                "documents": [
                  "http://dip21.bundestag.de/dip21/btd/19/055/1905567.pdf"
                ]
              },
              {
                "line": "Sammelübersicht 127 auf <a target='_blank' href=\"http://dip21.bundestag.de/dip21/btd/19/055/1905568.pdf\" class=\"dipLink\" title=\"Die PDF-Datei Drucksache 19/5568 öffnet sich in einem neuen Fenster\"><i class=\"icon-doc\"></i>19/5568</a> angenommen",
                "documents": [
                  "http://dip21.bundestag.de/dip21/btd/19/055/1905568.pdf"
                ]
              },
              {
                "line": "Sammelübersicht 128 auf <a target='_blank' href=\"http://dip21.bundestag.de/dip21/btd/19/055/1905569.pdf\" class=\"dipLink\" title=\"Die PDF-Datei Drucksache 19/5569 öffnet sich in einem neuen Fenster\"><i class=\"icon-doc\"></i>19/5569</a> angenommen",
                "documents": [
                  "http://dip21.bundestag.de/dip21/btd/19/055/1905569.pdf"
                ]
              },
              {
                "line": "Sammelübersicht 129 auf <a target='_blank' href=\"http://dip21.bundestag.de/dip21/btd/19/055/1905570.pdf\" class=\"dipLink\" title=\"Die PDF-Datei Drucksache 19/5570 öffnet sich in einem neuen Fenster\"><i class=\"icon-doc\"></i>19/5570</a> angenommen",
                "documents": [
                  "http://dip21.bundestag.de/dip21/btd/19/055/1905570.pdf"
                ]
              },
              {
                "line": "Sammelübersicht 130 auf <a target='_blank' href=\"http://dip21.bundestag.de/dip21/btd/19/055/1905571.pdf\" class=\"dipLink\" title=\"Die PDF-Datei Drucksache 19/5571 öffnet sich in einem neuen Fenster\"><i class=\"icon-doc\"></i>19/5571</a> angenommen",
                "documents": [
                  "http://dip21.bundestag.de/dip21/btd/19/055/1905571.pdf"
                ]
              },
              {
                "line": "Sammelübersicht 131 auf <a target='_blank' href=\"http://dip21.bundestag.de/dip21/btd/19/055/1905572.pdf\" class=\"dipLink\" title=\"Die PDF-Datei Drucksache 19/5572 öffnet sich in einem neuen Fenster\"><i class=\"icon-doc\"></i>19/5572</a> angenommen",
                "documents": [
                  "http://dip21.bundestag.de/dip21/btd/19/055/1905572.pdf"
                ]
              },
              {
                "line": "Sammelübersicht 132 auf <a target='_blank' href=\"http://dip21.bundestag.de/dip21/btd/19/055/1905573.pdf\" class=\"dipLink\" title=\"Die PDF-Datei Drucksache 19/5573 öffnet sich in einem neuen Fenster\"><i class=\"icon-doc\"></i>19/5573</a> angenommen",
                "documents": [
                  "http://dip21.bundestag.de/dip21/btd/19/055/1905573.pdf"
                ]
              },
              {
                "line": "Sammelübersicht 133 auf <a target='_blank' href=\"http://dip21.bundestag.de/dip21/btd/19/055/1905574.pdf\" class=\"dipLink\" title=\"Die PDF-Datei Drucksache 19/5574 öffnet sich in einem neuen Fenster\"><i class=\"icon-doc\"></i>19/5574</a> angenommen",
                "documents": [
                  "http://dip21.bundestag.de/dip21/btd/19/055/1905574.pdf"
                ]
              },
              {
                "line": "Sammelübersicht 134 auf <a target='_blank' href=\"http://dip21.bundestag.de/dip21/btd/19/055/1905575.pdf\" class=\"dipLink\" title=\"Die PDF-Datei Drucksache 19/5575 öffnet sich in einem neuen Fenster\"><i class=\"icon-doc\"></i>19/5575</a> angenommen",
                "documents": [
                  "http://dip21.bundestag.de/dip21/btd/19/055/1905575.pdf"
                ]
              },
              {
                "line": "Sammelübersicht 135 auf <a target='_blank' href=\"http://dip21.bundestag.de/dip21/btd/19/055/1905576.pdf\" class=\"dipLink\" title=\"Die PDF-Datei Drucksache 19/5576 öffnet sich in einem neuen Fenster\"><i class=\"icon-doc\"></i>19/5576</a> angenommen",
                "documents": [
                  "http://dip21.bundestag.de/dip21/btd/19/055/1905576.pdf"
                ]
              },
              {
                "line": "Sammelübersicht 136 auf <a target='_blank' href=\"http://dip21.bundestag.de/dip21/btd/19/055/1905577.pdf\" class=\"dipLink\" title=\"Die PDF-Datei Drucksache 19/5577 öffnet sich in einem neuen Fenster\"><i class=\"icon-doc\"></i>19/5577</a> angenommen",
                "documents": [
                  "http://dip21.bundestag.de/dip21/btd/19/055/1905577.pdf"
                ]
              },
              {
                "line": "Gesetzentwurf <a target='_blank' href=\"http://dip21.bundestag.de/dip21/btd/19/049/1904950.pdf\" class=\"dipLink\" title=\"Die PDF-Datei Drucksache 19/4950 öffnet sich in einem neuen Fenster\"><i class=\"icon-doc\"></i>19/4950</a> und <a target='_blank' href=\"http://dip21.bundestag.de/dip21/btd/19/054/1905420.pdf\" class=\"dipLink\" title=\"Die PDF-Datei Drucksache 19/5420 öffnet sich in einem neuen Fenster\"><i class=\"icon-doc\"></i>19/5420</a> (Beschlussempfehlung <a target='_blank' href=\"http://dip21.bundestag.de/dip21/btd/19/056/1905682.pdf\" class=\"dipLink\" title=\"Die PDF-Datei Drucksache 19/5682 öffnet sich in einem neuen Fenster\"><i class=\"icon-doc\"></i>19/5682</a>: Gesetzentwurf in Ausschussfassung annehmen) angenommen",
                "documents": [
                  "http://dip21.bundestag.de/dip21/btd/19/049/1904950.pdf",
                  "http://dip21.bundestag.de/dip21/btd/19/054/1905420.pdf",
                  "http://dip21.bundestag.de/dip21/btd/19/056/1905682.pdf"
                ]
              },
              {
                "line": "Antrag <a target='_blank' href=\"http://dip21.bundestag.de/dip21/btd/19/059/1905910.pdf\" class=\"dipLink\" title=\"Die PDF-Datei Drucksache 19/5910 öffnet sich in einem neuen Fenster\"><i class=\"icon-doc\"></i>19/5910</a> abgelehnt",
                "documents": [
                  "http://dip21.bundestag.de/dip21/btd/19/059/1905910.pdf"
                ]
              }
            ]
          },
          {
            "time": "2018-11-22T13:05:00.000Z",
            "top": "I.16",
            "heading": "Familie, Senioren, Frauen und Jugend",
            "article": "https://www.bundestag.de/dokumente/textarchiv/2018/kw47-de-familie-senioren-frauen-jugend-576938",
            "topic": [
              {
                "lines": [
                  "Beschlussempfehlungen und Berichte des Haushaltsausschusses",
                  "(8. Ausschuss)",
                  "hier: Einzelplan 17",
                  "Bundesministerium für Familie, Senioren, Frauen und Jugend",
                  "Drucksache <a target='_blank' href=\"http://dip21.bundestag.de/dip21/btd/19/046/1904624.pdf\" class=\"dipLink\" title=\"Die PDF-Datei Drucksache 19/4624 öffnet sich in einem neuen Fenster\"><i class=\"icon-doc\"></i>19/4624</a>, <a target='_blank' href=\"http://dip21.bundestag.de/dip21/btd/19/046/1904625.pdf\" class=\"dipLink\" title=\"Die PDF-Datei Drucksache 19/4625 öffnet sich in einem neuen Fenster\"><i class=\"icon-doc\"></i>19/4625</a>"
                ],
                "documents": [
                  "http://dip21.bundestag.de/dip21/btd/19/046/1904624.pdf",
                  "http://dip21.bundestag.de/dip21/btd/19/046/1904625.pdf"
                ]
              }
            ],
            "status": [
              {
                "line": "Einzelplan 17 (Beschlussempfehlung <a target='_blank' href=\"http://dip21.bundestag.de/dip21/btd/19/046/1904624.pdf\" class=\"dipLink\" title=\"Die PDF-Datei Drucksache 19/4624 öffnet sich in einem neuen Fenster\"><i class=\"icon-doc\"></i>19/4624</a> und <a target='_blank' href=\"http://dip21.bundestag.de/dip21/btd/19/046/1904625.pdf\" class=\"dipLink\" title=\"Die PDF-Datei Drucksache 19/4625 öffnet sich in einem neuen Fenster\"><i class=\"icon-doc\"></i>19/4625</a>) in der Ausschussfassung angenommen",
                "documents": [
                  "http://dip21.bundestag.de/dip21/btd/19/046/1904624.pdf",
                  "http://dip21.bundestag.de/dip21/btd/19/046/1904625.pdf"
                ]
              }
            ]
          },
          {
            "time": "2018-11-22T16:50:00.000Z",
            "top": "ZP 4",
            "heading": "Antrag auf Genehmigung zur Durchführung eines Disziplinarverfahrens",
            "article": "https://www.bundestag.de/dokumente/textarchiv/2018/kw47-de-immunitaet-579016",
            "topic": [
              {
                "lines": [
                  "Antrag auf Genehmigung zur Durchführung eines Disziplinarverfahrens",
                  "Drucksache <a target='_blank' href=\"http://dip21.bundestag.de/dip21/btd/19/059/1905958.pdf\" class=\"dipLink\" title=\"Die PDF-Datei Drucksache 19/5958 öffnet sich in einem neuen Fenster\"><i class=\"icon-doc\"></i>19/5958</a>"
                ],
                "documents": [
                  "http://dip21.bundestag.de/dip21/btd/19/059/1905958.pdf"
                ]
              }
            ],
            "status": [
              {
                "line": "Abstimmung über den soeben aufgesetzten ZP 4",
                "documents": []
              },
              {
                "line": "Beschlussempfehlung <a target='_blank' href=\"http://dip21.bundestag.de/dip21/btd/19/059/1905958.pdf\" class=\"dipLink\" title=\"Die PDF-Datei Drucksache 19/5958 öffnet sich in einem neuen Fenster\"><i class=\"icon-doc\"></i>19/5958</a> (Antrag auf Genehmigung zur Durchführung eines Disziplinarverfahrens) angenommen",
                "documents": [
                  "http://dip21.bundestag.de/dip21/btd/19/059/1905958.pdf"
                ]
              }
            ]
          }
        ]
      },
      {
        "date": "2018-11-23T00:00:00.000Z",
        "dateText": "23. November 2018",
        "session": "66",
        "tops": [
          {
            "time": "2018-11-23T09:00:00.000Z",
            "top": "I.18",
            "heading": "Arbeit und Soziales",
            "article": "https://www.bundestag.de/dokumente/textarchiv/2018/kw47-de-arbeit-soziales-576954",
            "topic": [
              {
                "lines": [
                  "Beschlussempfehlungen und Berichte des Haushaltsausschusses (8. Ausschuss)",
                  "hier: Einzelplan 11",
                  "Bundesministerium für Arbeit und Soziales",
                  "Drucksache <a target='_blank' href=\"http://dip21.bundestag.de/dip21/btd/19/046/1904611.pdf\" class=\"dipLink\" title=\"Die PDF-Datei Drucksache 19/4611 öffnet sich in einem neuen Fenster\"><i class=\"icon-doc\"></i>19/4611</a>, <a target='_blank' href=\"http://dip21.bundestag.de/dip21/btd/19/046/1904624.pdf\" class=\"dipLink\" title=\"Die PDF-Datei Drucksache 19/4624 öffnet sich in einem neuen Fenster\"><i class=\"icon-doc\"></i>19/4624</a>"
                ],
                "documents": [
                  "http://dip21.bundestag.de/dip21/btd/19/046/1904611.pdf",
                  "http://dip21.bundestag.de/dip21/btd/19/046/1904624.pdf"
                ]
              }
            ],
            "status": [
              {
                "line": "Einzelplan 11 (Beschlussempfehlung <a target='_blank' href=\"http://dip21.bundestag.de/dip21/btd/19/046/1904611.pdf\" class=\"dipLink\" title=\"Die PDF-Datei Drucksache 19/4611 öffnet sich in einem neuen Fenster\"><i class=\"icon-doc\"></i>19/4611</a> und <a target='_blank' href=\"http://dip21.bundestag.de/dip21/btd/19/046/1904624.pdf\" class=\"dipLink\" title=\"Die PDF-Datei Drucksache 19/4624 öffnet sich in einem neuen Fenster\"><i class=\"icon-doc\"></i>19/4624</a>) in der Ausschussfassung angenommen",
                "documents": [
                  "http://dip21.bundestag.de/dip21/btd/19/046/1904611.pdf",
                  "http://dip21.bundestag.de/dip21/btd/19/046/1904624.pdf"
                ]
              }
            ]
          },
          {
            "time": "2018-11-23T10:40:00.000Z",
            "top": "I.20",
            "heading": "Allgemeine Finanzverwaltung",
            "article": "https://www.bundestag.de/dokumente/textarchiv/2018/kw47-de-allgemeine-finanzverwaltung-576962",
            "topic": [
              {
                "lines": [
                  "Beschlussempfehlungen und Berichte des Haushaltsausschusses (8. Ausschuss)",
                  "hier: Einzelplan 60",
                  "Allgemeine Finanzverwaltung",
                  "Drucksache <a target='_blank' href=\"http://dip21.bundestag.de/dip21/btd/19/046/1904623.pdf\" class=\"dipLink\" title=\"Die PDF-Datei Drucksache 19/4623 öffnet sich in einem neuen Fenster\"><i class=\"icon-doc\"></i>19/4623</a>"
                ],
                "documents": [
                  "http://dip21.bundestag.de/dip21/btd/19/046/1904623.pdf"
                ]
              },
              {
                "lines": [
                  "Namentliche Abstimmung"
                ],
                "documents": []
              }
            ],
            "status": [
              {
                "line": "Änderungsantrag <a target='_blank' href=\"http://dip21.bundestag.de/dip21/btd/19/059/1905900.pdf\" class=\"dipLink\" title=\"Die PDF-Datei Drucksache 19/5900 öffnet sich in einem neuen Fenster\"><i class=\"icon-doc\"></i>19/5900</a> abgelehnt",
                "documents": [
                  "http://dip21.bundestag.de/dip21/btd/19/059/1905900.pdf"
                ]
              },
              {
                "line": "Änderungsantrag <a target='_blank' href=\"http://dip21.bundestag.de/dip21/btd/19/059/1905902.pdf\" class=\"dipLink\" title=\"Die PDF-Datei Drucksache 19/5902 öffnet sich in einem neuen Fenster\"><i class=\"icon-doc\"></i>19/5902</a> abgelehnt",
                "documents": [
                  "http://dip21.bundestag.de/dip21/btd/19/059/1905902.pdf"
                ]
              },
              {
                "line": "Änderungsantrag <a target='_blank' href=\"http://dip21.bundestag.de/dip21/btd/19/058/1905850.pdf\" class=\"dipLink\" title=\"Die PDF-Datei Drucksache 19/5850 öffnet sich in einem neuen Fenster\"><i class=\"icon-doc\"></i>19/5850</a> abgelehnt",
                "documents": [
                  "http://dip21.bundestag.de/dip21/btd/19/058/1905850.pdf"
                ]
              },
              {
                "line": "namentliche Abstimmung über Änderungsantrag <a target='_blank' href=\"http://dip21.bundestag.de/dip21/btd/19/059/1905901.pdf\" class=\"dipLink\" title=\"Die PDF-Datei Drucksache 19/5901 öffnet sich in einem neuen Fenster\"><i class=\"icon-doc\"></i>19/5901</a>",
                "documents": [
                  "http://dip21.bundestag.de/dip21/btd/19/059/1905901.pdf"
                ]
              },
              {
                "line": "10:45:20: Beginn der namentlichen Abstimmung",
                "documents": []
              },
              {
                "line": "10:48:29: Ende der namentlichen Abstimmung",
                "documents": []
              },
              {
                "line": "Gesamt: 624 Ja: 270 Nein: 353 Enthaltungen: 1",
                "documents": []
              },
              {
                "line": "10:48:48: Beginn der Sitzungsunterbrechung",
                "documents": []
              },
              {
                "line": "10:55:15: Ende der Sitzungsunterbrechung",
                "documents": []
              },
              {
                "line": "Änderungsantrag <a target='_blank' href=\"http://dip21.bundestag.de/dip21/btd/19/059/1905901.pdf\" class=\"dipLink\" title=\"Die PDF-Datei Drucksache 19/5901 öffnet sich in einem neuen Fenster\"><i class=\"icon-doc\"></i>19/5901</a> abgelehnt",
                "documents": [
                  "http://dip21.bundestag.de/dip21/btd/19/059/1905901.pdf"
                ]
              },
              {
                "line": "Einzelplan 60 (Beschlussempfehlung <a target='_blank' href=\"http://dip21.bundestag.de/dip21/btd/19/046/1904623.pdf\" class=\"dipLink\" title=\"Die PDF-Datei Drucksache 19/4623 öffnet sich in einem neuen Fenster\"><i class=\"icon-doc\"></i>19/4623</a>) in der Ausschussfassung angenommen",
                "documents": [
                  "http://dip21.bundestag.de/dip21/btd/19/046/1904623.pdf"
                ]
              }
            ]
          },
          {
            "time": "2018-11-23T10:55:00.000Z",
            "top": "II.",
            "heading": "Haushaltsgesetz 2019",
            "article": "https://www.bundestag.de/dokumente/textarchiv/2018/kw47-de-haushaltsgesetz-2019-dritte-lesung-576966",
            "topic": [
              {
                "lines": [
                  "Dritte Beratung des von der Bundesregierung eingebrachten Entwurfs eines Gesetzes über die Feststellung des Bundeshaushaltsplans für das Haushaltsjahr 2019 (Haushaltsgesetz 2019)",
                  "Drucksachen <a target='_blank' href=\"http://dip21.bundestag.de/dip21/btd/19/034/1903400.pdf\" class=\"dipLink\" title=\"Die PDF-Datei Drucksache 19/3400 öffnet sich in einem neuen Fenster\"><i class=\"icon-doc\"></i>19/3400</a>, <a target='_blank' href=\"http://dip21.bundestag.de/dip21/btd/19/034/1903402.pdf\" class=\"dipLink\" title=\"Die PDF-Datei Drucksache 19/3402 öffnet sich in einem neuen Fenster\"><i class=\"icon-doc\"></i>19/3402</a>, <a target='_blank' href=\"http://dip21.bundestag.de/dip21/btd/19/046/1904601.pdf\" class=\"dipLink\" title=\"Die PDF-Datei Drucksache 19/4601 öffnet sich in einem neuen Fenster\"><i class=\"icon-doc\"></i>19/4601</a>, <a target='_blank' href=\"http://dip21.bundestag.de/dip21/btd/19/046/1904602.pdf\" class=\"dipLink\" title=\"Die PDF-Datei Drucksache 19/4602 öffnet sich in einem neuen Fenster\"><i class=\"icon-doc\"></i>19/4602</a>, <a target='_blank' href=\"http://dip21.bundestag.de/dip21/btd/19/046/1904605.pdf\" class=\"dipLink\" title=\"Die PDF-Datei Drucksache 19/4605 öffnet sich in einem neuen Fenster\"><i class=\"icon-doc\"></i>19/4605</a>, <a target='_blank' href=\"http://dip21.bundestag.de/dip21/btd/19/046/1904606.pdf\" class=\"dipLink\" title=\"Die PDF-Datei Drucksache 19/4606 öffnet sich in einem neuen Fenster\"><i class=\"icon-doc\"></i>19/4606</a>, <a target='_blank' href=\"http://dip21.bundestag.de/dip21/btd/19/046/1904607.pdf\" class=\"dipLink\" title=\"Die PDF-Datei Drucksache 19/4607 öffnet sich in einem neuen Fenster\"><i class=\"icon-doc\"></i>19/4607</a>, <a target='_blank' href=\"http://dip21.bundestag.de/dip21/btd/19/046/1904609.pdf\" class=\"dipLink\" title=\"Die PDF-Datei Drucksache 19/4609 öffnet sich in einem neuen Fenster\"><i class=\"icon-doc\"></i>19/4609</a>, <a target='_blank' href=\"http://dip21.bundestag.de/dip21/btd/19/046/1904611.pdf\" class=\"dipLink\" title=\"Die PDF-Datei Drucksache 19/4611 öffnet sich in einem neuen Fenster\"><i class=\"icon-doc\"></i>19/4611</a>, <a target='_blank' href=\"http://dip21.bundestag.de/dip21/btd/19/046/1904612.pdf\" class=\"dipLink\" title=\"Die PDF-Datei Drucksache 19/4612 öffnet sich in einem neuen Fenster\"><i class=\"icon-doc\"></i>19/4612</a>, <a target='_blank' href=\"http://dip21.bundestag.de/dip21/btd/19/046/1904613.pdf\" class=\"dipLink\" title=\"Die PDF-Datei Drucksache 19/4613 öffnet sich in einem neuen Fenster\"><i class=\"icon-doc\"></i>19/4613</a>, <a target='_blank' href=\"http://dip21.bundestag.de/dip21/btd/19/046/1904617.pdf\" class=\"dipLink\" title=\"Die PDF-Datei Drucksache 19/4617 öffnet sich in einem neuen Fenster\"><i class=\"icon-doc\"></i>19/4617</a>, <a target='_blank' href=\"http://dip21.bundestag.de/dip21/btd/19/046/1904620.pdf\" class=\"dipLink\" title=\"Die PDF-Datei Drucksache 19/4620 öffnet sich in einem neuen Fenster\"><i class=\"icon-doc\"></i>19/4620</a>, <a target='_blank' href=\"http://dip21.bundestag.de/dip21/btd/19/046/1904621.pdf\" class=\"dipLink\" title=\"Die PDF-Datei Drucksache 19/4621 öffnet sich in einem neuen Fenster\"><i class=\"icon-doc\"></i>19/4621</a>, <a target='_blank' href=\"http://dip21.bundestag.de/dip21/btd/19/046/1904622.pdf\" class=\"dipLink\" title=\"Die PDF-Datei Drucksache 19/4622 öffnet sich in einem neuen Fenster\"><i class=\"icon-doc\"></i>19/4622</a>, <a target='_blank' href=\"http://dip21.bundestag.de/dip21/btd/19/046/1904623.pdf\" class=\"dipLink\" title=\"Die PDF-Datei Drucksache 19/4623 öffnet sich in einem neuen Fenster\"><i class=\"icon-doc\"></i>19/4623</a>, <a target='_blank' href=\"http://dip21.bundestag.de/dip21/btd/19/046/1904624.pdf\" class=\"dipLink\" title=\"Die PDF-Datei Drucksache 19/4624 öffnet sich in einem neuen Fenster\"><i class=\"icon-doc\"></i>19/4624</a>, <a target='_blank' href=\"http://dip21.bundestag.de/dip21/btd/19/046/1904625.pdf\" class=\"dipLink\" title=\"Die PDF-Datei Drucksache 19/4625 öffnet sich in einem neuen Fenster\"><i class=\"icon-doc\"></i>19/4625</a>, <a target='_blank' href=\"http://dip21.bundestag.de/dip21/btd/19/046/1904626.pdf\" class=\"dipLink\" title=\"Die PDF-Datei Drucksache 19/4626 öffnet sich in einem neuen Fenster\"><i class=\"icon-doc\"></i>19/4626</a>"
                ],
                "documents": [
                  "http://dip21.bundestag.de/dip21/btd/19/034/1903400.pdf",
                  "http://dip21.bundestag.de/dip21/btd/19/034/1903402.pdf",
                  "http://dip21.bundestag.de/dip21/btd/19/046/1904601.pdf",
                  "http://dip21.bundestag.de/dip21/btd/19/046/1904602.pdf",
                  "http://dip21.bundestag.de/dip21/btd/19/046/1904605.pdf",
                  "http://dip21.bundestag.de/dip21/btd/19/046/1904606.pdf",
                  "http://dip21.bundestag.de/dip21/btd/19/046/1904607.pdf",
                  "http://dip21.bundestag.de/dip21/btd/19/046/1904609.pdf",
                  "http://dip21.bundestag.de/dip21/btd/19/046/1904611.pdf",
                  "http://dip21.bundestag.de/dip21/btd/19/046/1904612.pdf",
                  "http://dip21.bundestag.de/dip21/btd/19/046/1904613.pdf",
                  "http://dip21.bundestag.de/dip21/btd/19/046/1904617.pdf",
                  "http://dip21.bundestag.de/dip21/btd/19/046/1904620.pdf",
                  "http://dip21.bundestag.de/dip21/btd/19/046/1904621.pdf",
                  "http://dip21.bundestag.de/dip21/btd/19/046/1904622.pdf",
                  "http://dip21.bundestag.de/dip21/btd/19/046/1904623.pdf",
                  "http://dip21.bundestag.de/dip21/btd/19/046/1904624.pdf",
                  "http://dip21.bundestag.de/dip21/btd/19/046/1904625.pdf",
                  "http://dip21.bundestag.de/dip21/btd/19/046/1904626.pdf"
                ]
              },
              {
                "lines": [
                  "Namentliche Abstimmungen"
                ],
                "documents": []
              }
            ],
            "status": [
              {
                "line": "namentliche Abstimmung über Haushaltgesetz 2019 <a target='_blank' href=\"http://dip21.bundestag.de/dip21/btd/19/034/1903400.pdf\" class=\"dipLink\" title=\"Die PDF-Datei Drucksache 19/3400 öffnet sich in einem neuen Fenster\"><i class=\"icon-doc\"></i>19/3400</a>, <a target='_blank' href=\"http://dip21.bundestag.de/dip21/btd/19/034/1903402.pdf\" class=\"dipLink\" title=\"Die PDF-Datei Drucksache 19/3402 öffnet sich in einem neuen Fenster\"><i class=\"icon-doc\"></i>19/3402</a>, <a target='_blank' href=\"http://dip21.bundestag.de/dip21/btd/19/046/1904601.pdf\" class=\"dipLink\" title=\"Die PDF-Datei Drucksache 19/4601 öffnet sich in einem neuen Fenster\"><i class=\"icon-doc\"></i>19/4601</a>, <a target='_blank' href=\"http://dip21.bundestag.de/dip21/btd/19/046/1904602.pdf\" class=\"dipLink\" title=\"Die PDF-Datei Drucksache 19/4602 öffnet sich in einem neuen Fenster\"><i class=\"icon-doc\"></i>19/4602</a>, <a target='_blank' href=\"http://dip21.bundestag.de/dip21/btd/19/046/1904605.pdf\" class=\"dipLink\" title=\"Die PDF-Datei Drucksache 19/4605 öffnet sich in einem neuen Fenster\"><i class=\"icon-doc\"></i>19/4605</a> bis <a target='_blank' href=\"http://dip21.bundestag.de/dip21/btd/19/046/1904609.pdf\" class=\"dipLink\" title=\"Die PDF-Datei Drucksache 19/4609 öffnet sich in einem neuen Fenster\"><i class=\"icon-doc\"></i>19/4609</a>, <a target='_blank' href=\"http://dip21.bundestag.de/dip21/btd/19/046/1904611.pdf\" class=\"dipLink\" title=\"Die PDF-Datei Drucksache 19/4611 öffnet sich in einem neuen Fenster\"><i class=\"icon-doc\"></i>19/4611</a> bis <a target='_blank' href=\"http://dip21.bundestag.de/dip21/btd/19/046/1904613.pdf\" class=\"dipLink\" title=\"Die PDF-Datei Drucksache 19/4613 öffnet sich in einem neuen Fenster\"><i class=\"icon-doc\"></i>19/4613</a>, <a target='_blank' href=\"http://dip21.bundestag.de/dip21/btd/19/046/1904617.pdf\" class=\"dipLink\" title=\"Die PDF-Datei Drucksache 19/4617 öffnet sich in einem neuen Fenster\"><i class=\"icon-doc\"></i>19/4617</a> und <a target='_blank' href=\"http://dip21.bundestag.de/dip21/btd/19/046/1904620.pdf\" class=\"dipLink\" title=\"Die PDF-Datei Drucksache 19/4620 öffnet sich in einem neuen Fenster\"><i class=\"icon-doc\"></i>19/4620</a> bis <a target='_blank' href=\"http://dip21.bundestag.de/dip21/btd/19/046/1904626.pdf\" class=\"dipLink\" title=\"Die PDF-Datei Drucksache 19/4626 öffnet sich in einem neuen Fenster\"><i class=\"icon-doc\"></i>19/4626</a>",
                "documents": [
                  "http://dip21.bundestag.de/dip21/btd/19/034/1903400.pdf",
                  "http://dip21.bundestag.de/dip21/btd/19/034/1903402.pdf",
                  "http://dip21.bundestag.de/dip21/btd/19/046/1904601.pdf",
                  "http://dip21.bundestag.de/dip21/btd/19/046/1904602.pdf",
                  "http://dip21.bundestag.de/dip21/btd/19/046/1904605.pdf",
                  "http://dip21.bundestag.de/dip21/btd/19/046/1904609.pdf",
                  "http://dip21.bundestag.de/dip21/btd/19/046/1904611.pdf",
                  "http://dip21.bundestag.de/dip21/btd/19/046/1904613.pdf",
                  "http://dip21.bundestag.de/dip21/btd/19/046/1904617.pdf",
                  "http://dip21.bundestag.de/dip21/btd/19/046/1904620.pdf",
                  "http://dip21.bundestag.de/dip21/btd/19/046/1904626.pdf"
                ]
              },
              {
                "line": "12:41:59: Beginn der namentlichen Abstimmung",
                "documents": []
              },
              {
                "line": "12:46:42: Ende der namentlichen Abstimmung",
                "documents": []
              },
              {
                "line": "Gesamt: 650   Ja: 366   Nein: 284   Enthaltungen: 0",
                "documents": []
              },
              {
                "line": "Haushaltgesetz 2019 angenommen",
                "documents": []
              },
              {
                "line": "namentliche Abstimmung über Entschließungsantrag <a target='_blank' href=\"http://dip21.bundestag.de/dip21/btd/19/058/1905898.pdf\" class=\"dipLink\" title=\"Die PDF-Datei Drucksache 19/5898 öffnet sich in einem neuen Fenster\"><i class=\"icon-doc\"></i>19/5898</a>",
                "documents": [
                  "http://dip21.bundestag.de/dip21/btd/19/058/1905898.pdf"
                ]
              },
              {
                "line": "12:47:13: Beginn der namentlichen Abstimmung",
                "documents": []
              },
              {
                "line": "12:50:54: Ende der namentlichen Abstimmung",
                "documents": []
              },
              {
                "line": "korrigiertes Ergebnis",
                "documents": []
              },
              {
                "line": "Gesamt: 644   Ja: 215   Nein: 369   Enthaltungen: 60",
                "documents": []
              },
              {
                "line": "Entschließungsantrag <a target='_blank' href=\"http://dip21.bundestag.de/dip21/btd/19/058/1905898.pdf\" class=\"dipLink\" title=\"Die PDF-Datei Drucksache 19/5898 öffnet sich in einem neuen Fenster\"><i class=\"icon-doc\"></i>19/5898</a> abgelehnt",
                "documents": [
                  "http://dip21.bundestag.de/dip21/btd/19/058/1905898.pdf"
                ]
              },
              {
                "line": "Entschließungsantrag <a target='_blank' href=\"http://dip21.bundestag.de/dip21/btd/19/059/1905912.pdf\" class=\"dipLink\" title=\"Die PDF-Datei Drucksache 19/5912 öffnet sich in einem neuen Fenster\"><i class=\"icon-doc\"></i>19/5912</a> abgelehnt",
                "documents": [
                  "http://dip21.bundestag.de/dip21/btd/19/059/1905912.pdf"
                ]
              },
              {
                "line": "Entschließungsantrag <a target='_blank' href=\"http://dip21.bundestag.de/dip21/btd/19/059/1905913.pdf\" class=\"dipLink\" title=\"Die PDF-Datei Drucksache 19/5913 öffnet sich in einem neuen Fenster\"><i class=\"icon-doc\"></i>19/5913</a> abgelehnt",
                "documents": [
                  "http://dip21.bundestag.de/dip21/btd/19/059/1905913.pdf"
                ]
              },
              {
                "line": "Entschließungsantrag <a target='_blank' href=\"http://dip21.bundestag.de/dip21/btd/19/059/1905914.pdf\" class=\"dipLink\" title=\"Die PDF-Datei Drucksache 19/5914 öffnet sich in einem neuen Fenster\"><i class=\"icon-doc\"></i>19/5914</a> abgelehnt",
                "documents": [
                  "http://dip21.bundestag.de/dip21/btd/19/059/1905914.pdf"
                ]
              },
              {
                "line": "Entschließungsantrag <a target='_blank' href=\"http://dip21.bundestag.de/dip21/btd/19/059/1905915.pdf\" class=\"dipLink\" title=\"Die PDF-Datei Drucksache 19/5915 öffnet sich in einem neuen Fenster\"><i class=\"icon-doc\"></i>19/5915</a> abgelehnt",
                "documents": [
                  "http://dip21.bundestag.de/dip21/btd/19/059/1905915.pdf"
                ]
              },
              {
                "line": "Entschließungsantrag <a target='_blank' href=\"http://dip21.bundestag.de/dip21/btd/19/059/1905916.pdf\" class=\"dipLink\" title=\"Die PDF-Datei Drucksache 19/5916 öffnet sich in einem neuen Fenster\"><i class=\"icon-doc\"></i>19/5916</a> abgelehnt",
                "documents": [
                  "http://dip21.bundestag.de/dip21/btd/19/059/1905916.pdf"
                ]
              },
              {
                "line": "Entschließungsantrag <a target='_blank' href=\"http://dip21.bundestag.de/dip21/btd/19/059/1905917.pdf\" class=\"dipLink\" title=\"Die PDF-Datei Drucksache 19/5917 öffnet sich in einem neuen Fenster\"><i class=\"icon-doc\"></i>19/5917</a> abgelehnt",
                "documents": [
                  "http://dip21.bundestag.de/dip21/btd/19/059/1905917.pdf"
                ]
              },
              {
                "line": "Entschließungsantrag <a target='_blank' href=\"http://dip21.bundestag.de/dip21/btd/19/059/1905918.pdf\" class=\"dipLink\" title=\"Die PDF-Datei Drucksache 19/5918 öffnet sich in einem neuen Fenster\"><i class=\"icon-doc\"></i>19/5918</a> abgelehnt",
                "documents": [
                  "http://dip21.bundestag.de/dip21/btd/19/059/1905918.pdf"
                ]
              },
              {
                "line": "Entschließungsantrag <a target='_blank' href=\"http://dip21.bundestag.de/dip21/btd/19/059/1905919.pdf\" class=\"dipLink\" title=\"Die PDF-Datei Drucksache 19/5919 öffnet sich in einem neuen Fenster\"><i class=\"icon-doc\"></i>19/5919</a> abgelehnt",
                "documents": [
                  "http://dip21.bundestag.de/dip21/btd/19/059/1905919.pdf"
                ]
              },
              {
                "line": "Entschließungsantrag <a target='_blank' href=\"http://dip21.bundestag.de/dip21/btd/19/059/1905920.pdf\" class=\"dipLink\" title=\"Die PDF-Datei Drucksache 19/5920 öffnet sich in einem neuen Fenster\"><i class=\"icon-doc\"></i>19/5920</a> abgelehnt",
                "documents": [
                  "http://dip21.bundestag.de/dip21/btd/19/059/1905920.pdf"
                ]
              },
              {
                "line": "Entschließungsantrag <a target='_blank' href=\"http://dip21.bundestag.de/dip21/btd/19/058/1905897.pdf\" class=\"dipLink\" title=\"Die PDF-Datei Drucksache 19/5897 öffnet sich in einem neuen Fenster\"><i class=\"icon-doc\"></i>19/5897</a> abgelehnt",
                "documents": [
                  "http://dip21.bundestag.de/dip21/btd/19/058/1905897.pdf"
                ]
              },
              {
                "line": "Entschließungsantrag <a target='_blank' href=\"http://dip21.bundestag.de/dip21/btd/19/058/1905899.pdf\" class=\"dipLink\" title=\"Die PDF-Datei Drucksache 19/5899 öffnet sich in einem neuen Fenster\"><i class=\"icon-doc\"></i>19/5899</a> abgelehnt",
                "documents": [
                  "http://dip21.bundestag.de/dip21/btd/19/058/1905899.pdf"
                ]
              },
              {
                "line": "Entschließungsantrag <a target='_blank' href=\"http://dip21.bundestag.de/dip21/btd/19/059/1905903.pdf\" class=\"dipLink\" title=\"Die PDF-Datei Drucksache 19/5903 öffnet sich in einem neuen Fenster\"><i class=\"icon-doc\"></i>19/5903</a> abgelehnt",
                "documents": [
                  "http://dip21.bundestag.de/dip21/btd/19/059/1905903.pdf"
                ]
              },
              {
                "line": "Entschließungsantrag <a target='_blank' href=\"http://dip21.bundestag.de/dip21/btd/19/059/1905904.pdf\" class=\"dipLink\" title=\"Die PDF-Datei Drucksache 19/5904 öffnet sich in einem neuen Fenster\"><i class=\"icon-doc\"></i>19/5904</a> abgelehnt",
                "documents": [
                  "http://dip21.bundestag.de/dip21/btd/19/059/1905904.pdf"
                ]
              },
              {
                "line": "Entschließungsantrag <a target='_blank' href=\"http://dip21.bundestag.de/dip21/btd/19/058/1905842.pdf\" class=\"dipLink\" title=\"Die PDF-Datei Drucksache 19/5842 öffnet sich in einem neuen Fenster\"><i class=\"icon-doc\"></i>19/5842</a> abgelehnt",
                "documents": [
                  "http://dip21.bundestag.de/dip21/btd/19/058/1905842.pdf"
                ]
              },
              {
                "line": "Entschließungsantrag <a target='_blank' href=\"http://dip21.bundestag.de/dip21/btd/19/058/1905843.pdf\" class=\"dipLink\" title=\"Die PDF-Datei Drucksache 19/5843 öffnet sich in einem neuen Fenster\"><i class=\"icon-doc\"></i>19/5843</a> abgelehnt",
                "documents": [
                  "http://dip21.bundestag.de/dip21/btd/19/058/1905843.pdf"
                ]
              },
              {
                "line": "Entschließungsantrag <a target='_blank' href=\"http://dip21.bundestag.de/dip21/btd/19/058/1905844.pdf\" class=\"dipLink\" title=\"Die PDF-Datei Drucksache 19/5844 öffnet sich in einem neuen Fenster\"><i class=\"icon-doc\"></i>19/5844</a> abgelehnt",
                "documents": [
                  "http://dip21.bundestag.de/dip21/btd/19/058/1905844.pdf"
                ]
              },
              {
                "line": "Entschließungsantrag <a target='_blank' href=\"http://dip21.bundestag.de/dip21/btd/19/058/1905845.pdf\" class=\"dipLink\" title=\"Die PDF-Datei Drucksache 19/5845 öffnet sich in einem neuen Fenster\"><i class=\"icon-doc\"></i>19/5845</a> abgelehnt",
                "documents": [
                  "http://dip21.bundestag.de/dip21/btd/19/058/1905845.pdf"
                ]
              },
              {
                "line": "Entschließungsantrag <a target='_blank' href=\"http://dip21.bundestag.de/dip21/btd/19/058/1905846.pdf\" class=\"dipLink\" title=\"Die PDF-Datei Drucksache 19/5846 öffnet sich in einem neuen Fenster\"><i class=\"icon-doc\"></i>19/5846</a> abgelehnt",
                "documents": [
                  "http://dip21.bundestag.de/dip21/btd/19/058/1905846.pdf"
                ]
              },
              {
                "line": "Entschließungsantrag <a target='_blank' href=\"http://dip21.bundestag.de/dip21/btd/19/058/1905847.pdf\" class=\"dipLink\" title=\"Die PDF-Datei Drucksache 19/5847 öffnet sich in einem neuen Fenster\"><i class=\"icon-doc\"></i>19/5847</a> abgelehnt",
                "documents": [
                  "http://dip21.bundestag.de/dip21/btd/19/058/1905847.pdf"
                ]
              },
              {
                "line": "Entschließungsantrag <a target='_blank' href=\"http://dip21.bundestag.de/dip21/btd/19/058/1905848.pdf\" class=\"dipLink\" title=\"Die PDF-Datei Drucksache 19/5848 öffnet sich in einem neuen Fenster\"><i class=\"icon-doc\"></i>19/5848</a> abgelehnt",
                "documents": [
                  "http://dip21.bundestag.de/dip21/btd/19/058/1905848.pdf"
                ]
              },
              {
                "line": "Entschließungsantrag <a target='_blank' href=\"http://dip21.bundestag.de/dip21/btd/19/058/1905849.pdf\" class=\"dipLink\" title=\"Die PDF-Datei Drucksache 19/5849 öffnet sich in einem neuen Fenster\"><i class=\"icon-doc\"></i>19/5849</a> (neu) abgelehnt",
                "documents": [
                  "http://dip21.bundestag.de/dip21/btd/19/058/1905849.pdf"
                ]
              },
              {
                "line": "Entschließungsantrag <a target='_blank' href=\"http://dip21.bundestag.de/dip21/btd/19/058/1905851.pdf\" class=\"dipLink\" title=\"Die PDF-Datei Drucksache 19/5851 öffnet sich in einem neuen Fenster\"><i class=\"icon-doc\"></i>19/5851</a> abgelehnt",
                "documents": [
                  "http://dip21.bundestag.de/dip21/btd/19/058/1905851.pdf"
                ]
              },
              {
                "line": "Entschließungsantrag <a target='_blank' href=\"http://dip21.bundestag.de/dip21/btd/19/058/1905852.pdf\" class=\"dipLink\" title=\"Die PDF-Datei Drucksache 19/5852 öffnet sich in einem neuen Fenster\"><i class=\"icon-doc\"></i>19/5852</a> abgelehnt",
                "documents": [
                  "http://dip21.bundestag.de/dip21/btd/19/058/1905852.pdf"
                ]
              },
              {
                "line": "Entschließungsantrag <a target='_blank' href=\"http://dip21.bundestag.de/dip21/btd/19/058/1905859.pdf\" class=\"dipLink\" title=\"Die PDF-Datei Drucksache 19/5859 öffnet sich in einem neuen Fenster\"><i class=\"icon-doc\"></i>19/5859</a> abgelehnt",
                "documents": [
                  "http://dip21.bundestag.de/dip21/btd/19/058/1905859.pdf"
                ]
              },
              {
                "line": "Entschließungsantrag <a target='_blank' href=\"http://dip21.bundestag.de/dip21/btd/19/058/1905896.pdf\" class=\"dipLink\" title=\"Die PDF-Datei Drucksache 19/5896 öffnet sich in einem neuen Fenster\"><i class=\"icon-doc\"></i>19/5896</a> abgelehnt",
                "documents": [
                  "http://dip21.bundestag.de/dip21/btd/19/058/1905896.pdf"
                ]
              },
              {
                "line": "Entschließungsantrag <a target='_blank' href=\"http://dip21.bundestag.de/dip21/btd/19/059/1905905.pdf\" class=\"dipLink\" title=\"Die PDF-Datei Drucksache 19/5905 öffnet sich in einem neuen Fenster\"><i class=\"icon-doc\"></i>19/5905</a> abgelehnt",
                "documents": [
                  "http://dip21.bundestag.de/dip21/btd/19/059/1905905.pdf"
                ]
              },
              {
                "line": "13:01:58: gibt Ergebnisse der namentlichen Abstimmungen bekannt",
                "documents": []
              }
            ]
          }
        ]
      }
    ]
  }
}